Workbook

Sheet Lista de ECs
F3: Exclusivo para cadastro de Filiais | AP3: Documento de Identidade (Opcional, mas se algum campo for preenchido, todos serão obrigatórios) * Obrigatório se operação PIX for marcada como SIM. | BE3: EXCLUSIVO para Liquidação de Ecs | BW3: Obrigatório em caso de CNP – Cartão não Presente ou Ambos | BY3: Ecs já cadastrados na Global Payments
B4: Informações do Estabelecimento Comercial | Q4: Contato do Estabelecimento Comercial | W4: Endereço do Estabelecimento Comercial | AF4: Informações do Responsável (Sócio) | AU4: Endereço do Responsável | BE4: Dados Bancários | BQ4: Taxas | BS4: Consultor Comercial | BU4: Informações de Operação
B5: Nome Fantasia * | C5: Nome / Razão Social * | D5: CNPJ/CPF * | E5: Tipo de Estabelecimento * | F5: Matriz (CNPJ) | G5: CNAE * | H5: MCC * | I5: Natureza Jurídica * | J5: Código (N.J) * | K5: Formato Jurídico * | L5: Data de Abertura * | M5: Dias de Funcionamento * | N5: Horário de funcionamento * | O5: Receita * | Q5: Email * | R5: Código de área * | S5: Número do Telefone * | T5: Tipo de telefone * | U5: Phone Type | W5: Rua/Av. * | X5: Número * | Y5: Complemento | Z5: Bairro * | AA5: CEP * | AB5: Cidade * | AC5: Estado * | AD5: País * | AF5: Nome Completo * | AG5: CPF * | AH5: Data de Nascimento * | AI5: Email * | AJ5: PEP * | AK5: Código de área * | AL5: Telefone * | AM5: Tipo de telefone * | AN5: Phone Type | AO5: Nome da Mãe * | AP5: Número do RG | AQ5: Data de emissão | AR5: Órgão expedidor | AS5: UF | AU5: Rua/Av. * | AV5: Número * | AW5: Complemento | AX5: Bairro * | AY5: CEP * | AZ5: Cidade * | BA5: Estado * | BB5: País * | BE5: Nome / Razão Social * | BF5: CNPJ/CPF * | BG5: Tipo PF/PJ * | BH5: Banco * | BI5: Código | BJ5: Agência * | BK5: Dígito da Agência | BL5: Conta * | BM5: Dígito da Conta* | BN5: Tipo de conta * | BO5: Account type | BQ5: Código da Tabela * | BS5: Matrícula do Consultor | BU5: Método de Processamento do Cartão * | BV5: PIX * | BW5: URL | BX5: Tema do Estabelecimento | BY5: MID | BZ5: TID | CA5: Token CNP | CB5: Fuso horário do terminal | CC5: Tap On Phone * | CD5: Perfil de Acesso * | CE5: TEF *
E6: =IF(LEN(D6)=11,"PF",IF(LEN(D6)=14,"PJ","")) | H6: =IF(G6<>"",VLOOKUP(G6,'Cnae mcc id'!$A:$M,9,0),"") | J6: =IF(I6<>"",VLOOKUP(I6,'Legal Nature'!$E$2:$G$84,3,0),"") | T6: =IF(LEFT(S6,1)="9","Celular",IF(S6="","","Fixo")) | U6: =IF( T6<>"",VLOOKUP(T6,Selects!$M$4:$N$1000,2,0),"") | AD6: =IF(AC6<>"",VLOOKUP(AC6,Selects!$B$4:$C$100,2,0),"") | AM6: =IF(LEFT(AL6,1)="9","Celular",IF(AL6="","","Fixo")) | AN6: =IF( AM6<>"",VLOOKUP(AM6,Selects!$M$4:$N$1000,2,0),"") | BB6: =IF(BA6<>"",VLOOKUP(BA6,Selects!$B$4:$C$100,2,0),"") | BG6: =IF(LEN(BF6)=11,"PF",IF(LEN(BF6)=14,"PJ","")) | BI6: =IF(BH6<>"",VLOOKUP(BH6,Selects!$G:$H,2,0),"") | BO6: =IF(BN6<>"",VLOOKUP(BN6,Selects!$J$4:$K$1000,2,0),"") | CB6: =IF(AC6<>"",VLOOKUP(AC6,Selects!$B:$E,4,0),"")
E7: =IF(LEN(D7)=11,"PF",IF(LEN(D7)=14,"PJ","")) | H7: =IF(G7<>"",VLOOKUP(G7,'Cnae mcc id'!$A:$M,9,0),"") | J7: =IF(I7<>"",VLOOKUP(I7,'Legal Nature'!$E$2:$G$84,3,0),"") | T7: =IF(LEFT(S7,1)="9","Celular",IF(S7="","","Fixo")) | U7: =IF( T7<>"",VLOOKUP(T7,Selects!$M$4:$N$1000,2,0),"") | AD7: =IF(AC7<>"",VLOOKUP(AC7,Selects!$B$4:$C$100,2,0),"") | AM7: =IF(LEFT(AL7,1)="9","Celular",IF(AL7="","","Fixo")) | AN7: =IF( AM7<>"",VLOOKUP(AM7,Selects!$M$4:$N$1000,2,0),"") | BB7: =IF(BA7<>"",VLOOKUP(BA7,Selects!$B$4:$C$100,2,0),"") | BG7: =IF(LEN(BF7)=11,"PF",IF(LEN(BF7)=14,"PJ","")) | BI7: =IF(BH7<>"",VLOOKUP(BH7,Selects!$G:$H,2,0),"") | BO7: =IF(BN7<>"",VLOOKUP(BN7,Selects!$J$4:$K$1000,2,0),"") | CB7: =IF(AC7<>"",VLOOKUP(AC7,Selects!$B:$E,4,0),"")
E8: =IF(LEN(D8)=11,"PF",IF(LEN(D8)=14,"PJ","")) | H8: =IF(G8<>"",VLOOKUP(G8,'Cnae mcc id'!$A:$M,9,0),"") | J8: =IF(I8<>"",VLOOKUP(I8,'Legal Nature'!$E$2:$G$84,3,0),"") | T8: =IF(LEFT(S8,1)="9","Celular",IF(S8="","","Fixo")) | U8: =IF( T8<>"",VLOOKUP(T8,Selects!$M$4:$N$1000,2,0),"") | AD8: =IF(AC8<>"",VLOOKUP(AC8,Selects!$B$4:$C$100,2,0),"") | AM8: =IF(LEFT(AL8,1)="9","Celular",IF(AL8="","","Fixo")) | AN8: =IF( AM8<>"",VLOOKUP(AM8,Selects!$M$4:$N$1000,2,0),"") | BB8: =IF(BA8<>"",VLOOKUP(BA8,Selects!$B$4:$C$100,2,0),"") | BG8: =IF(LEN(BF8)=11,"PF",IF(LEN(BF8)=14,"PJ","")) | BI8: =IF(BH8<>"",VLOOKUP(BH8,Selects!$G:$H,2,0),"") | BO8: =IF(BN8<>"",VLOOKUP(BN8,Selects!$J$4:$K$1000,2,0),"") | CB8: =IF(AC8<>"",VLOOKUP(AC8,Selects!$B:$E,4,0),"")
E9: =IF(LEN(D9)=11,"PF",IF(LEN(D9)=14,"PJ","")) | H9: =IF(G9<>"",VLOOKUP(G9,'Cnae mcc id'!$A:$M,9,0),"") | J9: =IF(I9<>"",VLOOKUP(I9,'Legal Nature'!$E$2:$G$84,3,0),"") | T9: =IF(LEFT(S9,1)="9","Celular",IF(S9="","","Fixo")) | U9: =IF( T9<>"",VLOOKUP(T9,Selects!$M$4:$N$1000,2,0),"") | AD9: =IF(AC9<>"",VLOOKUP(AC9,Selects!$B$4:$C$100,2,0),"") | AM9: =IF(LEFT(AL9,1)="9","Celular",IF(AL9="","","Fixo")) | AN9: =IF( AM9<>"",VLOOKUP(AM9,Selects!$M$4:$N$1000,2,0),"") | BB9: =IF(BA9<>"",VLOOKUP(BA9,Selects!$B$4:$C$100,2,0),"") | BG9: =IF(LEN(BF9)=11,"PF",IF(LEN(BF9)=14,"PJ","")) | BI9: =IF(BH9<>"",VLOOKUP(BH9,Selects!$G:$H,2,0),"") | BO9: =IF(BN9<>"",VLOOKUP(BN9,Selects!$J$4:$K$1000,2,0),"") | CB9: =IF(AC9<>"",VLOOKUP(AC9,Selects!$B:$E,4,0),"")
E10: =IF(LEN(D10)=11,"PF",IF(LEN(D10)=14,"PJ","")) | H10: =IF(G10<>"",VLOOKUP(G10,'Cnae mcc id'!$A:$M,9,0),"") | J10: =IF(I10<>"",VLOOKUP(I10,'Legal Nature'!$E$2:$G$84,3,0),"") | T10: =IF(LEFT(S10,1)="9","Celular",IF(S10="","","Fixo")) | U10: =IF( T10<>"",VLOOKUP(T10,Selects!$M$4:$N$1000,2,0),"") | AD10: =IF(AC10<>"",VLOOKUP(AC10,Selects!$B$4:$C$100,2,0),"") | AM10: =IF(LEFT(AL10,1)="9","Celular",IF(AL10="","","Fixo")) | AN10: =IF( AM10<>"",VLOOKUP(AM10,Selects!$M$4:$N$1000,2,0),"") | BB10: =IF(BA10<>"",VLOOKUP(BA10,Selects!$B$4:$C$100,2,0),"") | BG10: =IF(LEN(BF10)=11,"PF",IF(LEN(BF10)=14,"PJ","")) | BI10: =IF(BH10<>"",VLOOKUP(BH10,Selects!$G:$H,2,0),"") | BO10: =IF(BN10<>"",VLOOKUP(BN10,Selects!$J$4:$K$1000,2,0),"") | CB10: =IF(AC10<>"",VLOOKUP(AC10,Selects!$B:$E,4,0),"")
E11: =IF(LEN(D11)=11,"PF",IF(LEN(D11)=14,"PJ","")) | H11: =IF(G11<>"",VLOOKUP(G11,'Cnae mcc id'!$A:$M,9,0),"") | J11: =IF(I11<>"",VLOOKUP(I11,'Legal Nature'!$E$2:$G$84,3,0),"") | T11: =IF(LEFT(S11,1)="9","Celular",IF(S11="","","Fixo")) | U11: =IF( T11<>"",VLOOKUP(T11,Selects!$M$4:$N$1000,2,0),"") | AD11: =IF(AC11<>"",VLOOKUP(AC11,Selects!$B$4:$C$100,2,0),"") | AM11: =IF(LEFT(AL11,1)="9","Celular",IF(AL11="","","Fixo")) | AN11: =IF( AM11<>"",VLOOKUP(AM11,Selects!$M$4:$N$1000,2,0),"") | BB11: =IF(BA11<>"",VLOOKUP(BA11,Selects!$B$4:$C$100,2,0),"") | BG11: =IF(LEN(BF11)=11,"PF",IF(LEN(BF11)=14,"PJ","")) | BI11: =IF(BH11<>"",VLOOKUP(BH11,Selects!$G:$H,2,0),"") | BO11: =IF(BN11<>"",VLOOKUP(BN11,Selects!$J$4:$K$1000,2,0),"") | CB11: =IF(AC11<>"",VLOOKUP(AC11,Selects!$B:$E,4,0),"")
E12: =IF(LEN(D12)=11,"PF",IF(LEN(D12)=14,"PJ","")) | H12: =IF(G12<>"",VLOOKUP(G12,'Cnae mcc id'!$A:$M,9,0),"") | J12: =IF(I12<>"",VLOOKUP(I12,'Legal Nature'!$E$2:$G$84,3,0),"") | T12: =IF(LEFT(S12,1)="9","Celular",IF(S12="","","Fixo")) | U12: =IF( T12<>"",VLOOKUP(T12,Selects!$M$4:$N$1000,2,0),"") | AD12: =IF(AC12<>"",VLOOKUP(AC12,Selects!$B$4:$C$100,2,0),"") | AM12: =IF(LEFT(AL12,1)="9","Celular",IF(AL12="","","Fixo")) | AN12: =IF( AM12<>"",VLOOKUP(AM12,Selects!$M$4:$N$1000,2,0),"") | BB12: =IF(BA12<>"",VLOOKUP(BA12,Selects!$B$4:$C$100,2,0),"") | BG12: =IF(LEN(BF12)=11,"PF",IF(LEN(BF12)=14,"PJ","")) | BI12: =IF(BH12<>"",VLOOKUP(BH12,Selects!$G:$H,2,0),"") | BO12: =IF(BN12<>"",VLOOKUP(BN12,Selects!$J$4:$K$1000,2,0),"") | CB12: =IF(AC12<>"",VLOOKUP(AC12,Selects!$B:$E,4,0),"")
E13: =IF(LEN(D13)=11,"PF",IF(LEN(D13)=14,"PJ","")) | H13: =IF(G13<>"",VLOOKUP(G13,'Cnae mcc id'!$A:$M,9,0),"") | J13: =IF(I13<>"",VLOOKUP(I13,'Legal Nature'!$E$2:$G$84,3,0),"") | T13: =IF(LEFT(S13,1)="9","Celular",IF(S13="","","Fixo")) | U13: =IF( T13<>"",VLOOKUP(T13,Selects!$M$4:$N$1000,2,0),"") | AD13: =IF(AC13<>"",VLOOKUP(AC13,Selects!$B$4:$C$100,2,0),"") | AM13: =IF(LEFT(AL13,1)="9","Celular",IF(AL13="","","Fixo")) | AN13: =IF( AM13<>"",VLOOKUP(AM13,Selects!$M$4:$N$1000,2,0),"") | BB13: =IF(BA13<>"",VLOOKUP(BA13,Selects!$B$4:$C$100,2,0),"") | BG13: =IF(LEN(BF13)=11,"PF",IF(LEN(BF13)=14,"PJ","")) | BI13: =IF(BH13<>"",VLOOKUP(BH13,Selects!$G:$H,2,0),"") | BO13: =IF(BN13<>"",VLOOKUP(BN13,Selects!$J$4:$K$1000,2,0),"") | CB13: =IF(AC13<>"",VLOOKUP(AC13,Selects!$B:$E,4,0),"")
E14: =IF(LEN(D14)=11,"PF",IF(LEN(D14)=14,"PJ","")) | H14: =IF(G14<>"",VLOOKUP(G14,'Cnae mcc id'!$A:$M,9,0),"") | J14: =IF(I14<>"",VLOOKUP(I14,'Legal Nature'!$E$2:$G$84,3,0),"") | T14: =IF(LEFT(S14,1)="9","Celular",IF(S14="","","Fixo")) | U14: =IF( T14<>"",VLOOKUP(T14,Selects!$M$4:$N$1000,2,0),"") | AD14: =IF(AC14<>"",VLOOKUP(AC14,Selects!$B$4:$C$100,2,0),"") | AM14: =IF(LEFT(AL14,1)="9","Celular",IF(AL14="","","Fixo")) | AN14: =IF( AM14<>"",VLOOKUP(AM14,Selects!$M$4:$N$1000,2,0),"") | BB14: =IF(BA14<>"",VLOOKUP(BA14,Selects!$B$4:$C$100,2,0),"") | BG14: =IF(LEN(BF14)=11,"PF",IF(LEN(BF14)=14,"PJ","")) | BI14: =IF(BH14<>"",VLOOKUP(BH14,Selects!$G:$H,2,0),"") | BO14: =IF(BN14<>"",VLOOKUP(BN14,Selects!$J$4:$K$1000,2,0),"") | CB14: =IF(AC14<>"",VLOOKUP(AC14,Selects!$B:$E,4,0),"")
E15: =IF(LEN(D15)=11,"PF",IF(LEN(D15)=14,"PJ","")) | H15: =IF(G15<>"",VLOOKUP(G15,'Cnae mcc id'!$A:$M,9,0),"") | J15: =IF(I15<>"",VLOOKUP(I15,'Legal Nature'!$E$2:$G$84,3,0),"") | T15: =IF(LEFT(S15,1)="9","Celular",IF(S15="","","Fixo")) | U15: =IF( T15<>"",VLOOKUP(T15,Selects!$M$4:$N$1000,2,0),"") | AD15: =IF(AC15<>"",VLOOKUP(AC15,Selects!$B$4:$C$100,2,0),"") | AM15: =IF(LEFT(AL15,1)="9","Celular",IF(AL15="","","Fixo")) | AN15: =IF( AM15<>"",VLOOKUP(AM15,Selects!$M$4:$N$1000,2,0),"") | BB15: =IF(BA15<>"",VLOOKUP(BA15,Selects!$B$4:$C$100,2,0),"") | BG15: =IF(LEN(BF15)=11,"PF",IF(LEN(BF15)=14,"PJ","")) | BI15: =IF(BH15<>"",VLOOKUP(BH15,Selects!$G:$H,2,0),"") | BO15: =IF(BN15<>"",VLOOKUP(BN15,Selects!$J$4:$K$1000,2,0),"") | CB15: =IF(AC15<>"",VLOOKUP(AC15,Selects!$B:$E,4,0),"")
E16: =IF(LEN(D16)=11,"PF",IF(LEN(D16)=14,"PJ","")) | H16: =IF(G16<>"",VLOOKUP(G16,'Cnae mcc id'!$A:$M,9,0),"") | J16: =IF(I16<>"",VLOOKUP(I16,'Legal Nature'!$E$2:$G$84,3,0),"") | T16: =IF(LEFT(S16,1)="9","Celular",IF(S16="","","Fixo")) | U16: =IF( T16<>"",VLOOKUP(T16,Selects!$M$4:$N$1000,2,0),"") | AD16: =IF(AC16<>"",VLOOKUP(AC16,Selects!$B$4:$C$100,2,0),"") | AM16: =IF(LEFT(AL16,1)="9","Celular",IF(AL16="","","Fixo")) | AN16: =IF( AM16<>"",VLOOKUP(AM16,Selects!$M$4:$N$1000,2,0),"") | BB16: =IF(BA16<>"",VLOOKUP(BA16,Selects!$B$4:$C$100,2,0),"") | BG16: =IF(LEN(BF16)=11,"PF",IF(LEN(BF16)=14,"PJ","")) | BI16: =IF(BH16<>"",VLOOKUP(BH16,Selects!$G:$H,2,0),"") | BO16: =IF(BN16<>"",VLOOKUP(BN16,Selects!$J$4:$K$1000,2,0),"") | CB16: =IF(AC16<>"",VLOOKUP(AC16,Selects!$B:$E,4,0),"")
E17: =IF(LEN(D17)=11,"PF",IF(LEN(D17)=14,"PJ","")) | H17: =IF(G17<>"",VLOOKUP(G17,'Cnae mcc id'!$A:$M,9,0),"") | J17: =IF(I17<>"",VLOOKUP(I17,'Legal Nature'!$E$2:$G$84,3,0),"") | T17: =IF(LEFT(S17,1)="9","Celular",IF(S17="","","Fixo")) | U17: =IF( T17<>"",VLOOKUP(T17,Selects!$M$4:$N$1000,2,0),"") | AD17: =IF(AC17<>"",VLOOKUP(AC17,Selects!$B$4:$C$100,2,0),"") | AM17: =IF(LEFT(AL17,1)="9","Celular",IF(AL17="","","Fixo")) | AN17: =IF( AM17<>"",VLOOKUP(AM17,Selects!$M$4:$N$1000,2,0),"") | BB17: =IF(BA17<>"",VLOOKUP(BA17,Selects!$B$4:$C$100,2,0),"") | BG17: =IF(LEN(BF17)=11,"PF",IF(LEN(BF17)=14,"PJ","")) | BI17: =IF(BH17<>"",VLOOKUP(BH17,Selects!$G:$H,2,0),"") | BO17: =IF(BN17<>"",VLOOKUP(BN17,Selects!$J$4:$K$1000,2,0),"") | CB17: =IF(AC17<>"",VLOOKUP(AC17,Selects!$B:$E,4,0),"")
... E998: =IF(LEN(D998)=11,"PF",IF(LEN(D998)=14,"PJ","")) | H998: =IF(G998<>"",VLOOKUP(G998,'Cnae mcc id'!$A:$M,9,0),"") | J998: =IF(I998<>"",VLOOKUP(I998,'Legal Nature'!$E$2:$G$84,3,0),"") | T998: =IF(LEFT(S998,1)="9","Celular",IF(S998="","","Fixo")) | U998: =IF( T998<>"",VLOOKUP(T998,Selects!$M$4:$N$1000,2,0),"") | AD998: =IF(AC998<>"",VLOOKUP(AC998,Selects!$B$4:$C$100,2,0),"") | AM998: =IF(LEFT(AL998,1)="9","Celular",IF(AL998="","","Fixo")) | AN998: =IF( AM998<>"",VLOOKUP(AM998,Selects!$M$4:$N$1000,2,0),"") | BB998: =IF(BA998<>"",VLOOKUP(BA998,Selects!$B$4:$C$100,2,0),"") | BG998: =IF(LEN(BF998)=11,"PF",IF(LEN(BF998)=14,"PJ","")) | BI998: =IF(BH998<>"",VLOOKUP(BH998,Selects!$G:$H,2,0),"") | BO998: =IF(BN998<>"",VLOOKUP(BN998,Selects!$J$4:$K$1000,2,0),"") | CB998: =IF(AC998<>"",VLOOKUP(AC998,Selects!$B:$E,4,0),"")
E999: =IF(LEN(D999)=11,"PF",IF(LEN(D999)=14,"PJ","")) | H999: =IF(G999<>"",VLOOKUP(G999,'Cnae mcc id'!$A:$M,9,0),"") | J999: =IF(I999<>"",VLOOKUP(I999,'Legal Nature'!$E$2:$G$84,3,0),"") | U999: =IF( T999<>"",VLOOKUP(T999,Selects!$M$4:$N$1000,2,0),"") | AD999: =IF(AC999<>"",VLOOKUP(AC999,Selects!$B$4:$C$100,2,0),"") | AM999: =IF(LEFT(AL999,1)="9","Celular",IF(AL999="","","Fixo")) | AN999: =IF( AM999<>"",VLOOKUP(AM999,Selects!$M$4:$N$1000,2,0),"") | BB999: =IF(BA999<>"",VLOOKUP(BA999,Selects!$B$4:$C$100,2,0),"") | BG999: =IF(LEN(BF999)=11,"PF",IF(LEN(BF999)=14,"PJ","")) | BI999: =IF(BH999<>"",VLOOKUP(BH999,Selects!$G:$H,2,0),"") | BO999: =IF(BN999<>"",VLOOKUP(BN999,Selects!$J$4:$K$1000,2,0),"") | CB999: =IF(AC999<>"",VLOOKUP(AC999,Selects!$B:$E,4,0),"")
E1000: =IF(LEN(D1000)=11,"PF",IF(LEN(D1000)=14,"PJ","")) | H1000: =IF(G1000<>"",VLOOKUP(G1000,'Cnae mcc id'!$A:$M,9,0),"") | J1000: =IF(I1000<>"",VLOOKUP(I1000,'Legal Nature'!$E$2:$G$84,3,0),"") | U1000: =IF( T1000<>"",VLOOKUP(T1000,Selects!$M$4:$N$1000,2,0),"") | AD1000: =IF(AC1000<>"",VLOOKUP(AC1000,Selects!$B$4:$C$100,2,0),"") | AM1000: =IF(LEFT(AL1000,1)="9","Celular",IF(AL1000="","","Fixo")) | AN1000: =IF( AM1000<>"",VLOOKUP(AM1000,Selects!$M$4:$N$1000,2,0),"") | BB1000: =IF(BA1000<>"",VLOOKUP(BA1000,Selects!$B$4:$C$100,2,0),"") | BG1000: =IF(LEN(BF1000)=11,"PF",IF(LEN(BF1000)=14,"PJ","")) | BI1000: =IF(BH1000<>"",VLOOKUP(BH1000,Selects!$G:$H,2,0),"") | BO1000: =IF(BN1000<>"",VLOOKUP(BN1000,Selects!$J$4:$K$1000,2,0),"") | CB1000: =IF(AC1000<>"",VLOOKUP(AC1000,Selects!$B:$E,4,0),"")
E1201: =IF(LEN(D1201)=11,"PF",IF(LEN(D1201)=14,"PJ","")) | H1201: =IF(G1201<>"",VLOOKUP(G1201,'Cnae mcc id'!$A:$M,9,0),"") | J1201: =IF(I1201<>"",VLOOKUP(I1201,'Legal Nature'!$E$2:$G$84,3,0),"") | U1201: =IF( T1201<>"",VLOOKUP(T1201,Selects!$M$4:$N$1000,2,0),"") | AD1201: =IF(AC1201<>"",VLOOKUP(AC1201,Selects!$B$4:$C$100,2,0),"") | AM1201: =IF(LEFT(AL1201,1)="9","Celular",IF(AL1201="","","Fixo")) | AN1201: =IF( AM1201<>"",VLOOKUP(AM1201,Selects!$M$4:$N$1000,2,0),"") | BB1201: =IF(BA1201<>"",VLOOKUP(BA1201,Selects!$B$4:$C$100,2,0),"") | BG1201: =IF(LEN(BF1201)=11,"PF",IF(LEN(BF1201)=14,"PJ","")) | BI1201: =IF(BH1201<>"",VLOOKUP(BH1201,Selects!$G:$H,2,0),"") | BO1201: =IF(BN1201<>"",VLOOKUP(BN1201,Selects!$J$4:$K$1000,2,0),"") | CB1201: =IF(AC1201<>"",VLOOKUP(AC1201,Selects!$B:$E,4,0),"")
E1202: =IF(LEN(D1202)=11,"PF",IF(LEN(D1202)=14,"PJ","")) | H1202: =IF(G1202<>"",VLOOKUP(G1202,'Cnae mcc id'!$A:$M,9,0),"") | J1202: =IF(I1202<>"",VLOOKUP(I1202,'Legal Nature'!$E$2:$G$84,3,0),"") | U1202: =IF( T1202<>"",VLOOKUP(T1202,Selects!$M$4:$N$1000,2,0),"") | AD1202: =IF(AC1202<>"",VLOOKUP(AC1202,Selects!$B$4:$C$100,2,0),"") | AM1202: =IF(LEFT(AL1202,1)="9","Celular",IF(AL1202="","","Fixo")) | AN1202: =IF( AM1202<>"",VLOOKUP(AM1202,Selects!$M$4:$N$1000,2,0),"") | BB1202: =IF(BA1202<>"",VLOOKUP(BA1202,Selects!$B$4:$C$100,2,0),"") | BG1202: =IF(LEN(BF1202)=11,"PF",IF(LEN(BF1202)=14,"PJ","")) | BI1202: =IF(BH1202<>"",VLOOKUP(BH1202,Selects!$G:$H,2,0),"") | BO1202: =IF(BN1202<>"",VLOOKUP(BN1202,Selects!$J$4:$K$1000,2,0),"") | CB1202: =IF(AC1202<>"",VLOOKUP(AC1202,Selects!$B:$E,4,0),"")
E1203: =IF(LEN(D1203)=11,"PF",IF(LEN(D1203)=14,"PJ","")) | H1203: =IF(G1203<>"",VLOOKUP(G1203,'Cnae mcc id'!$A:$M,9,0),"") | J1203: =IF(I1203<>"",VLOOKUP(I1203,'Legal Nature'!$E$2:$G$84,3,0),"") | U1203: =IF( T1203<>"",VLOOKUP(T1203,Selects!$M$4:$N$1000,2,0),"") | AD1203: =IF(AC1203<>"",VLOOKUP(AC1203,Selects!$B$4:$C$100,2,0),"") | AM1203: =IF(LEFT(AL1203,1)="9","Celular",IF(AL1203="","","Fixo")) | AN1203: =IF( AM1203<>"",VLOOKUP(AM1203,Selects!$M$4:$N$1000,2,0),"") | BB1203: =IF(BA1203<>"",VLOOKUP(BA1203,Selects!$B$4:$C$100,2,0),"") | BG1203: =IF(LEN(BF1203)=11,"PF",IF(LEN(BF1203)=14,"PJ","")) | BI1203: =IF(BH1203<>"",VLOOKUP(BH1203,Selects!$G:$H,2,0),"") | BO1203: =IF(BN1203<>"",VLOOKUP(BN1203,Selects!$J$4:$K$1000,2,0),"") | CB1203: =IF(AC1203<>"",VLOOKUP(AC1203,Selects!$B:$E,4,0),"")
E1204: =IF(LEN(D1204)=11,"PF",IF(LEN(D1204)=14,"PJ","")) | H1204: =IF(G1204<>"",VLOOKUP(G1204,'Cnae mcc id'!$A:$M,9,0),"") | J1204: =IF(I1204<>"",VLOOKUP(I1204,'Legal Nature'!$E$2:$G$84,3,0),"") | U1204: =IF( T1204<>"",VLOOKUP(T1204,Selects!$M$4:$N$1000,2,0),"") | AD1204: =IF(AC1204<>"",VLOOKUP(AC1204,Selects!$B$4:$C$100,2,0),"") | AM1204: =IF(LEFT(AL1204,1)="9","Celular",IF(AL1204="","","Fixo")) | AN1204: =IF( AM1204<>"",VLOOKUP(AM1204,Selects!$M$4:$N$1000,2,0),"") | BB1204: =IF(BA1204<>"",VLOOKUP(BA1204,Selects!$B$4:$C$100,2,0),"") | BG1204: =IF(LEN(BF1204)=11,"PF",IF(LEN(BF1204)=14,"PJ","")) | BI1204: =IF(BH1204<>"",VLOOKUP(BH1204,Selects!$G:$H,2,0),"") | BO1204: =IF(BN1204<>"",VLOOKUP(BN1204,Selects!$J$4:$K$1000,2,0),"") | CB1204: =IF(AC1204<>"",VLOOKUP(AC1204,Selects!$B:$E,4,0),"")
E1205: =IF(LEN(D1205)=11,"PF",IF(LEN(D1205)=14,"PJ","")) | H1205: =IF(G1205<>"",VLOOKUP(G1205,'Cnae mcc id'!$A:$M,9,0),"") | J1205: =IF(I1205<>"",VLOOKUP(I1205,'Legal Nature'!$E$2:$G$84,3,0),"") | U1205: =IF( T1205<>"",VLOOKUP(T1205,Selects!$M$4:$N$1000,2,0),"") | AD1205: =IF(AC1205<>"",VLOOKUP(AC1205,Selects!$B$4:$C$100,2,0),"") | AM1205: =IF(LEFT(AL1205,1)="9","Celular",IF(AL1205="","","Fixo")) | AN1205: =IF( AM1205<>"",VLOOKUP(AM1205,Selects!$M$4:$N$1000,2,0),"") | BB1205: =IF(BA1205<>"",VLOOKUP(BA1205,Selects!$B$4:$C$100,2,0),"") | BG1205: =IF(LEN(BF1205)=11,"PF",IF(LEN(BF1205)=14,"PJ","")) | BI1205: =IF(BH1205<>"",VLOOKUP(BH1205,Selects!$G:$H,2,0),"") | BO1205: =IF(BN1205<>"",VLOOKUP(BN1205,Selects!$J$4:$K$1000,2,0),"") | CB1205: =IF(AC1205<>"",VLOOKUP(AC1205,Selects!$B:$E,4,0),"")
E1206: =IF(LEN(D1206)=11,"PF",IF(LEN(D1206)=14,"PJ","")) | H1206: =IF(G1206<>"",VLOOKUP(G1206,'Cnae mcc id'!$A:$M,9,0),"") | J1206: =IF(I1206<>"",VLOOKUP(I1206,'Legal Nature'!$E$2:$G$84,3,0),"") | U1206: =IF( T1206<>"",VLOOKUP(T1206,Selects!$M$4:$N$1000,2,0),"") | AD1206: =IF(AC1206<>"",VLOOKUP(AC1206,Selects!$B$4:$C$100,2,0),"") | AM1206: =IF(LEFT(AL1206,1)="9","Celular",IF(AL1206="","","Fixo")) | AN1206: =IF( AM1206<>"",VLOOKUP(AM1206,Selects!$M$4:$N$1000,2,0),"") | BB1206: =IF(BA1206<>"",VLOOKUP(BA1206,Selects!$B$4:$C$100,2,0),"") | BG1206: =IF(LEN(BF1206)=11,"PF",IF(LEN(BF1206)=14,"PJ","")) | BI1206: =IF(BH1206<>"",VLOOKUP(BH1206,Selects!$G:$H,2,0),"") | BO1206: =IF(BN1206<>"",VLOOKUP(BN1206,Selects!$J$4:$K$1000,2,0),"") | CB1206: =IF(AC1206<>"",VLOOKUP(AC1206,Selects!$B:$E,4,0),"")
E1207: =IF(LEN(D1207)=11,"PF",IF(LEN(D1207)=14,"PJ","")) | H1207: =IF(G1207<>"",VLOOKUP(G1207,'Cnae mcc id'!$A:$M,9,0),"") | J1207: =IF(I1207<>"",VLOOKUP(I1207,'Legal Nature'!$E$2:$G$84,3,0),"") | U1207: =IF( T1207<>"",VLOOKUP(T1207,Selects!$M$4:$N$1000,2,0),"") | AD1207: =IF(AC1207<>"",VLOOKUP(AC1207,Selects!$B$4:$C$100,2,0),"") | AM1207: =IF(LEFT(AL1207,1)="9","Celular",IF(AL1207="","","Fixo")) | AN1207: =IF( AM1207<>"",VLOOKUP(AM1207,Selects!$M$4:$N$1000,2,0),"") | BB1207: =IF(BA1207<>"",VLOOKUP(BA1207,Selects!$B$4:$C$100,2,0),"") | BG1207: =IF(LEN(BF1207)=11,"PF",IF(LEN(BF1207)=14,"PJ","")) | BI1207: =IF(BH1207<>"",VLOOKUP(BH1207,Selects!$G:$H,2,0),"") | BO1207: =IF(BN1207<>"",VLOOKUP(BN1207,Selects!$J$4:$K$1000,2,0),"") | CB1207: =IF(AC1207<>"",VLOOKUP(AC1207,Selects!$B:$E,4,0),"")
E1208: =IF(LEN(D1208)=11,"PF",IF(LEN(D1208)=14,"PJ","")) | H1208: =IF(G1208<>"",VLOOKUP(G1208,'Cnae mcc id'!$A:$M,9,0),"") | J1208: =IF(I1208<>"",VLOOKUP(I1208,'Legal Nature'!$E$2:$G$84,3,0),"") | U1208: =IF( T1208<>"",VLOOKUP(T1208,Selects!$M$4:$N$1000,2,0),"") | AD1208: =IF(AC1208<>"",VLOOKUP(AC1208,Selects!$B$4:$C$100,2,0),"") | AM1208: =IF(LEFT(AL1208,1)="9","Celular",IF(AL1208="","","Fixo")) | AN1208: =IF( AM1208<>"",VLOOKUP(AM1208,Selects!$M$4:$N$1000,2,0),"") | BB1208: =IF(BA1208<>"",VLOOKUP(BA1208,Selects!$B$4:$C$100,2,0),"") | BG1208: =IF(LEN(BF1208)=11,"PF",IF(LEN(BF1208)=14,"PJ","")) | BI1208: =IF(BH1208<>"",VLOOKUP(BH1208,Selects!$G:$H,2,0),"") | BO1208: =IF(BN1208<>"",VLOOKUP(BN1208,Selects!$J$4:$K$1000,2,0),"") | CB1208: =IF(AC1208<>"",VLOOKUP(AC1208,Selects!$B:$E,4,0),"")
E1209: =IF(LEN(D1209)=11,"PF",IF(LEN(D1209)=14,"PJ","")) | H1209: =IF(G1209<>"",VLOOKUP(G1209,'Cnae mcc id'!$A:$M,9,0),"") | J1209: =IF(I1209<>"",VLOOKUP(I1209,'Legal Nature'!$E$2:$G$84,3,0),"") | U1209: =IF( T1209<>"",VLOOKUP(T1209,Selects!$M$4:$N$1000,2,0),"") | AD1209: =IF(AC1209<>"",VLOOKUP(AC1209,Selects!$B$4:$C$100,2,0),"") | AM1209: =IF(LEFT(AL1209,1)="9","Celular",IF(AL1209="","","Fixo")) | AN1209: =IF( AM1209<>"",VLOOKUP(AM1209,Selects!$M$4:$N$1000,2,0),"") | BB1209: =IF(BA1209<>"",VLOOKUP(BA1209,Selects!$B$4:$C$100,2,0),"") | BG1209: =IF(LEN(BF1209)=11,"PF",IF(LEN(BF1209)=14,"PJ","")) | BI1209: =IF(BH1209<>"",VLOOKUP(BH1209,Selects!$G:$H,2,0),"") | BO1209: =IF(BN1209<>"",VLOOKUP(BN1209,Selects!$J$4:$K$1000,2,0),"") | CB1209: =IF(AC1209<>"",VLOOKUP(AC1209,Selects!$B:$E,4,0),"")
E1210: =IF(LEN(D1210)=11,"PF",IF(LEN(D1210)=14,"PJ","")) | H1210: =IF(G1210<>"",VLOOKUP(G1210,'Cnae mcc id'!$A:$M,9,0),"") | J1210: =IF(I1210<>"",VLOOKUP(I1210,'Legal Nature'!$E$2:$G$84,3,0),"") | T1210: =IF(LEFT(S1210,1)="9","Celular",IF(S1210="","","Fixo")) | U1210: =IF( T1210<>"",VLOOKUP(T1210,Selects!$M$4:$N$1000,2,0),"") | AD1210: =IF(AC1210<>"",VLOOKUP(AC1210,Selects!$B$4:$C$100,2,0),"") | AM1210: =IF(LEFT(AL1210,1)="9","Celular",IF(AL1210="","","Fixo")) | AN1210: =IF( AM1210<>"",VLOOKUP(AM1210,Selects!$M$4:$N$1000,2,0),"") | BB1210: =IF(BA1210<>"",VLOOKUP(BA1210,Selects!$B$4:$C$100,2,0),"") | BG1210: =IF(LEN(BF1210)=11,"PF",IF(LEN(BF1210)=14,"PJ","")) | BI1210: =IF(BH1210<>"",VLOOKUP(BH1210,Selects!$G:$H,2,0),"") | BO1210: =IF(BN1210<>"",VLOOKUP(BN1210,Selects!$J$4:$K$1000,2,0),"") | CB1210: =IF(AC1210<>"",VLOOKUP(AC1210,Selects!$B:$E,4,0),"")
E1211: =IF(LEN(D1211)=11,"PF",IF(LEN(D1211)=14,"PJ","")) | H1211: =IF(G1211<>"",VLOOKUP(G1211,'Cnae mcc id'!$A:$M,9,0),"") | J1211: =IF(I1211<>"",VLOOKUP(I1211,'Legal Nature'!$E$2:$G$84,3,0),"") | T1211: =IF(LEFT(S1211,1)="9","Celular",IF(S1211="","","Fixo")) | U1211: =IF( T1211<>"",VLOOKUP(T1211,Selects!$M$4:$N$1000,2,0),"") | AD1211: =IF(AC1211<>"",VLOOKUP(AC1211,Selects!$B$4:$C$100,2,0),"") | AM1211: =IF(LEFT(AL1211,1)="9","Celular",IF(AL1211="","","Fixo")) | AN1211: =IF( AM1211<>"",VLOOKUP(AM1211,Selects!$M$4:$N$1000,2,0),"") | BB1211: =IF(BA1211<>"",VLOOKUP(BA1211,Selects!$B$4:$C$100,2,0),"") | BG1211: =IF(LEN(BF1211)=11,"PF",IF(LEN(BF1211)=14,"PJ","")) | BI1211: =IF(BH1211<>"",VLOOKUP(BH1211,Selects!$G:$H,2,0),"") | BO1211: =IF(BN1211<>"",VLOOKUP(BN1211,Selects!$J$4:$K$1000,2,0),"") | CB1211: =IF(AC1211<>"",VLOOKUP(AC1211,Selects!$B:$E,4,0),"")
E1212: =IF(LEN(D1212)=11,"PF",IF(LEN(D1212)=14,"PJ","")) | H1212: =IF(G1212<>"",VLOOKUP(G1212,'Cnae mcc id'!$A:$M,9,0),"") | J1212: =IF(I1212<>"",VLOOKUP(I1212,'Legal Nature'!$E$2:$G$84,3,0),"") | T1212: =IF(LEFT(S1212,1)="9","Celular",IF(S1212="","","Fixo")) | U1212: =IF( T1212<>"",VLOOKUP(T1212,Selects!$M$4:$N$1000,2,0),"") | AD1212: =IF(AC1212<>"",VLOOKUP(AC1212,Selects!$B$4:$C$100,2,0),"") | AM1212: =IF(LEFT(AL1212,1)="9","Celular",IF(AL1212="","","Fixo")) | AN1212: =IF( AM1212<>"",VLOOKUP(AM1212,Selects!$M$4:$N$1000,2,0),"") | BB1212: =IF(BA1212<>"",VLOOKUP(BA1212,Selects!$B$4:$C$100,2,0),"") | BG1212: =IF(LEN(BF1212)=11,"PF",IF(LEN(BF1212)=14,"PJ","")) | BI1212: =IF(BH1212<>"",VLOOKUP(BH1212,Selects!$G:$H,2,0),"") | BO1212: =IF(BN1212<>"",VLOOKUP(BN1212,Selects!$J$4:$K$1000,2,0),"") | CB1212: =IF(AC1212<>"",VLOOKUP(AC1212,Selects!$B:$E,4,0),"")
E1213: =IF(LEN(D1213)=11,"PF",IF(LEN(D1213)=14,"PJ","")) | H1213: =IF(G1213<>"",VLOOKUP(G1213,'Cnae mcc id'!$A:$M,9,0),"") | J1213: =IF(I1213<>"",VLOOKUP(I1213,'Legal Nature'!$E$2:$G$84,3,0),"") | T1213: =IF(LEFT(S1213,1)="9","Celular",IF(S1213="","","Fixo")) | U1213: =IF( T1213<>"",VLOOKUP(T1213,Selects!$M$4:$N$1000,2,0),"") | AD1213: =IF(AC1213<>"",VLOOKUP(AC1213,Selects!$B$4:$C$100,2,0),"") | AM1213: =IF(LEFT(AL1213,1)="9","Celular",IF(AL1213="","","Fixo")) | AN1213: =IF( AM1213<>"",VLOOKUP(AM1213,Selects!$M$4:$N$1000,2,0),"") | BB1213: =IF(BA1213<>"",VLOOKUP(BA1213,Selects!$B$4:$C$100,2,0),"") | BG1213: =IF(LEN(BF1213)=11,"PF",IF(LEN(BF1213)=14,"PJ","")) | BI1213: =IF(BH1213<>"",VLOOKUP(BH1213,Selects!$G:$H,2,0),"") | BO1213: =IF(BN1213<>"",VLOOKUP(BN1213,Selects!$J$4:$K$1000,2,0),"") | CB1213: =IF(AC1213<>"",VLOOKUP(AC1213,Selects!$B:$E,4,0),"")
E1214: =IF(LEN(D1214)=11,"PF",IF(LEN(D1214)=14,"PJ","")) | H1214: =IF(G1214<>"",VLOOKUP(G1214,'Cnae mcc id'!$A:$M,9,0),"") | J1214: =IF(I1214<>"",VLOOKUP(I1214,'Legal Nature'!$E$2:$G$84,3,0),"") | T1214: =IF(LEFT(S1214,1)="9","Celular",IF(S1214="","","Fixo")) | U1214: =IF( T1214<>"",VLOOKUP(T1214,Selects!$M$4:$N$1000,2,0),"") | AD1214: =IF(AC1214<>"",VLOOKUP(AC1214,Selects!$B$4:$C$100,2,0),"") | AM1214: =IF(LEFT(AL1214,1)="9","Celular",IF(AL1214="","","Fixo")) | AN1214: =IF( AM1214<>"",VLOOKUP(AM1214,Selects!$M$4:$N$1000,2,0),"") | BB1214: =IF(BA1214<>"",VLOOKUP(BA1214,Selects!$B$4:$C$100,2,0),"") | BG1214: =IF(LEN(BF1214)=11,"PF",IF(LEN(BF1214)=14,"PJ","")) | BI1214: =IF(BH1214<>"",VLOOKUP(BH1214,Selects!$G:$H,2,0),"") | BO1214: =IF(BN1214<>"",VLOOKUP(BN1214,Selects!$J$4:$K$1000,2,0),"") | CB1214: =IF(AC1214<>"",VLOOKUP(AC1214,Selects!$B:$E,4,0),"")
E1215: =IF(LEN(D1215)=11,"PF",IF(LEN(D1215)=14,"PJ","")) | H1215: =IF(G1215<>"",VLOOKUP(G1215,'Cnae mcc id'!$A:$M,9,0),"") | J1215: =IF(I1215<>"",VLOOKUP(I1215,'Legal Nature'!$E$2:$G$84,3,0),"") | T1215: =IF(LEFT(S1215,1)="9","Celular",IF(S1215="","","Fixo")) | U1215: =IF( T1215<>"",VLOOKUP(T1215,Selects!$M$4:$N$1000,2,0),"") | AD1215: =IF(AC1215<>"",VLOOKUP(AC1215,Selects!$B$4:$C$100,2,0),"") | AM1215: =IF(LEFT(AL1215,1)="9","Celular",IF(AL1215="","","Fixo")) | AN1215: =IF( AM1215<>"",VLOOKUP(AM1215,Selects!$M$4:$N$1000,2,0),"") | BB1215: =IF(BA1215<>"",VLOOKUP(BA1215,Selects!$B$4:$C$100,2,0),"") | BG1215: =IF(LEN(BF1215)=11,"PF",IF(LEN(BF1215)=14,"PJ","")) | BI1215: =IF(BH1215<>"",VLOOKUP(BH1215,Selects!$G:$H,2,0),"") | BO1215: =IF(BN1215<>"",VLOOKUP(BN1215,Selects!$J$4:$K$1000,2,0),"") | CB1215: =IF(AC1215<>"",VLOOKUP(AC1215,Selects!$B:$E,4,0),"")
E1216: =IF(LEN(D1216)=11,"PF",IF(LEN(D1216)=14,"PJ","")) | H1216: =IF(G1216<>"",VLOOKUP(G1216,'Cnae mcc id'!$A:$M,9,0),"") | J1216: =IF(I1216<>"",VLOOKUP(I1216,'Legal Nature'!$E$2:$G$84,3,0),"") | T1216: =IF(LEFT(S1216,1)="9","Celular",IF(S1216="","","Fixo")) | U1216: =IF( T1216<>"",VLOOKUP(T1216,Selects!$M$4:$N$1000,2,0),"") | AD1216: =IF(AC1216<>"",VLOOKUP(AC1216,Selects!$B$4:$C$100,2,0),"") | AM1216: =IF(LEFT(AL1216,1)="9","Celular",IF(AL1216="","","Fixo")) | AN1216: =IF( AM1216<>"",VLOOKUP(AM1216,Selects!$M$4:$N$1000,2,0),"") | BB1216: =IF(BA1216<>"",VLOOKUP(BA1216,Selects!$B$4:$C$100,2,0),"") | BG1216: =IF(LEN(BF1216)=11,"PF",IF(LEN(BF1216)=14,"PJ","")) | BI1216: =IF(BH1216<>"",VLOOKUP(BH1216,Selects!$G:$H,2,0),"") | BO1216: =IF(BN1216<>"",VLOOKUP(BN1216,Selects!$J$4:$K$1000,2,0),"") | CB1216: =IF(AC1216<>"",VLOOKUP(AC1216,Selects!$B:$E,4,0),"")
E1217: =IF(LEN(D1217)=11,"PF",IF(LEN(D1217)=14,"PJ","")) | H1217: =IF(G1217<>"",VLOOKUP(G1217,'Cnae mcc id'!$A:$M,9,0),"") | J1217: =IF(I1217<>"",VLOOKUP(I1217,'Legal Nature'!$E$2:$G$84,3,0),"") | T1217: =IF(LEFT(S1217,1)="9","Celular",IF(S1217="","","Fixo")) | U1217: =IF( T1217<>"",VLOOKUP(T1217,Selects!$M$4:$N$1000,2,0),"") | AD1217: =IF(AC1217<>"",VLOOKUP(AC1217,Selects!$B$4:$C$100,2,0),"") | AM1217: =IF(LEFT(AL1217,1)="9","Celular",IF(AL1217="","","Fixo")) | AN1217: =IF( AM1217<>"",VLOOKUP(AM1217,Selects!$M$4:$N$1000,2,0),"") | BB1217: =IF(BA1217<>"",VLOOKUP(BA1217,Selects!$B$4:$C$100,2,0),"") | BG1217: =IF(LEN(BF1217)=11,"PF",IF(LEN(BF1217)=14,"PJ","")) | BI1217: =IF(BH1217<>"",VLOOKUP(BH1217,Selects!$G:$H,2,0),"") | BO1217: =IF(BN1217<>"",VLOOKUP(BN1217,Selects!$J$4:$K$1000,2,0),"") | CB1217: =IF(AC1217<>"",VLOOKUP(AC1217,Selects!$B:$E,4,0),"")
E1218: =IF(LEN(D1218)=11,"PF",IF(LEN(D1218)=14,"PJ","")) | H1218: =IF(G1218<>"",VLOOKUP(G1218,'Cnae mcc id'!$A:$M,9,0),"") | J1218: =IF(I1218<>"",VLOOKUP(I1218,'Legal Nature'!$E$2:$G$84,3,0),"") | T1218: =IF(LEFT(S1218,1)="9","Celular",IF(S1218="","","Fixo")) | U1218: =IF( T1218<>"",VLOOKUP(T1218,Selects!$M$4:$N$1000,2,0),"") | AD1218: =IF(AC1218<>"",VLOOKUP(AC1218,Selects!$B$4:$C$100,2,0),"") | AM1218: =IF(LEFT(AL1218,1)="9","Celular",IF(AL1218="","","Fixo")) | AN1218: =IF( AM1218<>"",VLOOKUP(AM1218,Selects!$M$4:$N$1000,2,0),"") | BB1218: =IF(BA1218<>"",VLOOKUP(BA1218,Selects!$B$4:$C$100,2,0),"") | BG1218: =IF(LEN(BF1218)=11,"PF",IF(LEN(BF1218)=14,"PJ","")) | BI1218: =IF(BH1218<>"",VLOOKUP(BH1218,Selects!$G:$H,2,0),"") | BO1218: =IF(BN1218<>"",VLOOKUP(BN1218,Selects!$J$4:$K$1000,2,0),"") | CB1218: =IF(AC1218<>"",VLOOKUP(AC1218,Selects!$B:$E,4,0),"")
E1219: =IF(LEN(D1219)=11,"PF",IF(LEN(D1219)=14,"PJ","")) | H1219: =IF(G1219<>"",VLOOKUP(G1219,'Cnae mcc id'!$A:$M,9,0),"") | J1219: =IF(I1219<>"",VLOOKUP(I1219,'Legal Nature'!$E$2:$G$84,3,0),"") | T1219: =IF(LEFT(S1219,1)="9","Celular",IF(S1219="","","Fixo")) | U1219: =IF( T1219<>"",VLOOKUP(T1219,Selects!$M$4:$N$1000,2,0),"") | AD1219: =IF(AC1219<>"",VLOOKUP(AC1219,Selects!$B$4:$C$100,2,0),"") | AM1219: =IF(LEFT(AL1219,1)="9","Celular",IF(AL1219="","","Fixo")) | AN1219: =IF( AM1219<>"",VLOOKUP(AM1219,Selects!$M$4:$N$1000,2,0),"") | BB1219: =IF(BA1219<>"",VLOOKUP(BA1219,Selects!$B$4:$C$100,2,0),"") | BG1219: =IF(LEN(BF1219)=11,"PF",IF(LEN(BF1219)=14,"PJ","")) | BI1219: =IF(BH1219<>"",VLOOKUP(BH1219,Selects!$G:$H,2,0),"") | BO1219: =IF(BN1219<>"",VLOOKUP(BN1219,Selects!$J$4:$K$1000,2,0),"") | CB1219: =IF(AC1219<>"",VLOOKUP(AC1219,Selects!$B:$E,4,0),"")
E1220: =IF(LEN(D1220)=11,"PF",IF(LEN(D1220)=14,"PJ","")) | H1220: =IF(G1220<>"",VLOOKUP(G1220,'Cnae mcc id'!$A:$M,9,0),"") | J1220: =IF(I1220<>"",VLOOKUP(I1220,'Legal Nature'!$E$2:$G$84,3,0),"") | T1220: =IF(LEFT(S1220,1)="9","Celular",IF(S1220="","","Fixo")) | U1220: =IF( T1220<>"",VLOOKUP(T1220,Selects!$M$4:$N$1000,2,0),"") | AD1220: =IF(AC1220<>"",VLOOKUP(AC1220,Selects!$B$4:$C$100,2,0),"") | AM1220: =IF(LEFT(AL1220,1)="9","Celular",IF(AL1220="","","Fixo")) | AN1220: =IF( AM1220<>"",VLOOKUP(AM1220,Selects!$M$4:$N$1000,2,0),"") | BB1220: =IF(BA1220<>"",VLOOKUP(BA1220,Selects!$B$4:$C$100,2,0),"") | BG1220: =IF(LEN(BF1220)=11,"PF",IF(LEN(BF1220)=14,"PJ","")) | BI1220: =IF(BH1220<>"",VLOOKUP(BH1220,Selects!$G:$H,2,0),"") | BO1220: =IF(BN1220<>"",VLOOKUP(BN1220,Selects!$J$4:$K$1000,2,0),"") | CB1220: =IF(AC1220<>"",VLOOKUP(AC1220,Selects!$B:$E,4,0),"")
E1221: =IF(LEN(D1221)=11,"PF",IF(LEN(D1221)=14,"PJ","")) | H1221: =IF(G1221<>"",VLOOKUP(G1221,'Cnae mcc id'!$A:$M,9,0),"") | J1221: =IF(I1221<>"",VLOOKUP(I1221,'Legal Nature'!$E$2:$G$84,3,0),"") | T1221: =IF(LEFT(S1221,1)="9","Celular",IF(S1221="","","Fixo")) | U1221: =IF( T1221<>"",VLOOKUP(T1221,Selects!$M$4:$N$1000,2,0),"") | AD1221: =IF(AC1221<>"",VLOOKUP(AC1221,Selects!$B$4:$C$100,2,0),"") | AM1221: =IF(LEFT(AL1221,1)="9","Celular",IF(AL1221="","","Fixo")) | AN1221: =IF( AM1221<>"",VLOOKUP(AM1221,Selects!$M$4:$N$1000,2,0),"") | BB1221: =IF(BA1221<>"",VLOOKUP(BA1221,Selects!$B$4:$C$100,2,0),"") | BG1221: =IF(LEN(BF1221)=11,"PF",IF(LEN(BF1221)=14,"PJ","")) | BI1221: =IF(BH1221<>"",VLOOKUP(BH1221,Selects!$G:$H,2,0),"") | BO1221: =IF(BN1221<>"",VLOOKUP(BN1221,Selects!$J$4:$K$1000,2,0),"") | CB1221: =IF(AC1221<>"",VLOOKUP(AC1221,Selects!$B:$E,4,0),"")
... E1307: =IF(LEN(D1307)=11,"PF",IF(LEN(D1307)=14,"PJ","")) | H1307: =IF(G1307<>"",VLOOKUP(G1307,'Cnae mcc id'!$A:$M,9,0),"") | J1307: =IF(I1307<>"",VLOOKUP(I1307,'Legal Nature'!$E$2:$G$84,3,0),"") | T1307: =IF(LEFT(S1307,1)="9","Celular",IF(S1307="","","Fixo")) | U1307: =IF( T1307<>"",VLOOKUP(T1307,Selects!$M$4:$N$1000,2,0),"") | AD1307: =IF(AC1307<>"",VLOOKUP(AC1307,Selects!$B$4:$C$100,2,0),"") | AM1307: =IF(LEFT(AL1307,1)="9","Celular",IF(AL1307="","","Fixo")) | AN1307: =IF( AM1307<>"",VLOOKUP(AM1307,Selects!$M$4:$N$1000,2,0),"") | BB1307: =IF(BA1307<>"",VLOOKUP(BA1307,Selects!$B$4:$C$100,2,0),"") | BG1307: =IF(LEN(BF1307)=11,"PF",IF(LEN(BF1307)=14,"PJ","")) | BI1307: =IF(BH1307<>"",VLOOKUP(BH1307,Selects!$G:$H,2,0),"") | BO1307: =IF(BN1307<>"",VLOOKUP(BN1307,Selects!$J$4:$K$1000,2,0),"") | CB1307: =IF(AC1307<>"",VLOOKUP(AC1307,Selects!$B:$E,4,0),"")
E1308: =IF(LEN(D1308)=11,"PF",IF(LEN(D1308)=14,"PJ","")) | H1308: =IF(G1308<>"",VLOOKUP(G1308,'Cnae mcc id'!$A:$M,9,0),"") | J1308: =IF(I1308<>"",VLOOKUP(I1308,'Legal Nature'!$E$2:$G$84,3,0),"") | U1308: =IF( T1308<>"",VLOOKUP(T1308,Selects!$M$4:$N$1000,2,0),"") | AD1308: =IF(AC1308<>"",VLOOKUP(AC1308,Selects!$B$4:$C$100,2,0),"") | AM1308: =IF(LEFT(AL1308,1)="9","Celular",IF(AL1308="","","Fixo")) | AN1308: =IF( AM1308<>"",VLOOKUP(AM1308,Selects!$M$4:$N$1000,2,0),"") | BB1308: =IF(BA1308<>"",VLOOKUP(BA1308,Selects!$B$4:$C$100,2,0),"") | BG1308: =IF(LEN(BF1308)=11,"PF",IF(LEN(BF1308)=14,"PJ","")) | BI1308: =IF(BH1308<>"",VLOOKUP(BH1308,Selects!$G:$H,2,0),"") | BO1308: =IF(BN1308<>"",VLOOKUP(BN1308,Selects!$J$4:$K$1000,2,0),"") | CB1308: =IF(AC1308<>"",VLOOKUP(AC1308,Selects!$B:$E,4,0),"")
E1309: =IF(LEN(D1309)=11,"PF",IF(LEN(D1309)=14,"PJ","")) | H1309: =IF(G1309<>"",VLOOKUP(G1309,'Cnae mcc id'!$A:$M,9,0),"") | J1309: =IF(I1309<>"",VLOOKUP(I1309,'Legal Nature'!$E$2:$G$84,3,0),"") | U1309: =IF( T1309<>"",VLOOKUP(T1309,Selects!$M$4:$N$1000,2,0),"") | AD1309: =IF(AC1309<>"",VLOOKUP(AC1309,Selects!$B$4:$C$100,2,0),"") | AM1309: =IF(LEFT(AL1309,1)="9","Celular",IF(AL1309="","","Fixo")) | AN1309: =IF( AM1309<>"",VLOOKUP(AM1309,Selects!$M$4:$N$1000,2,0),"") | BB1309: =IF(BA1309<>"",VLOOKUP(BA1309,Selects!$B$4:$C$100,2,0),"") | BG1309: =IF(LEN(BF1309)=11,"PF",IF(LEN(BF1309)=14,"PJ","")) | BI1309: =IF(BH1309<>"",VLOOKUP(BH1309,Selects!$G:$H,2,0),"") | BO1309: =IF(BN1309<>"",VLOOKUP(BN1309,Selects!$J$4:$K$1000,2,0),"") | CB1309: =IF(AC1309<>"",VLOOKUP(AC1309,Selects!$B:$E,4,0),"")
E1310: =IF(LEN(D1310)=11,"PF",IF(LEN(D1310)=14,"PJ","")) | H1310: =IF(G1310<>"",VLOOKUP(G1310,'Cnae mcc id'!$A:$M,9,0),"") | J1310: =IF(I1310<>"",VLOOKUP(I1310,'Legal Nature'!$E$2:$G$84,3,0),"") | U1310: =IF( T1310<>"",VLOOKUP(T1310,Selects!$M$4:$N$1000,2,0),"") | AD1310: =IF(AC1310<>"",VLOOKUP(AC1310,Selects!$B$4:$C$100,2,0),"") | AM1310: =IF(LEFT(AL1310,1)="9","Celular",IF(AL1310="","","Fixo")) | AN1310: =IF( AM1310<>"",VLOOKUP(AM1310,Selects!$M$4:$N$1000,2,0),"") | BB1310: =IF(BA1310<>"",VLOOKUP(BA1310,Selects!$B$4:$C$100,2,0),"") | BG1310: =IF(LEN(BF1310)=11,"PF",IF(LEN(BF1310)=14,"PJ","")) | BI1310: =IF(BH1310<>"",VLOOKUP(BH1310,Selects!$G:$H,2,0),"") | BO1310: =IF(BN1310<>"",VLOOKUP(BN1310,Selects!$J$4:$K$1000,2,0),"") | CB1310: =IF(AC1310<>"",VLOOKUP(AC1310,Selects!$B:$E,4,0),"")
E1311: =IF(LEN(D1311)=11,"PF",IF(LEN(D1311)=14,"PJ","")) | H1311: =IF(G1311<>"",VLOOKUP(G1311,'Cnae mcc id'!$A:$M,9,0),"") | J1311: =IF(I1311<>"",VLOOKUP(I1311,'Legal Nature'!$E$2:$G$84,3,0),"") | U1311: =IF( T1311<>"",VLOOKUP(T1311,Selects!$M$4:$N$1000,2,0),"") | AD1311: =IF(AC1311<>"",VLOOKUP(AC1311,Selects!$B$4:$C$100,2,0),"") | AM1311: =IF(LEFT(AL1311,1)="9","Celular",IF(AL1311="","","Fixo")) | AN1311: =IF( AM1311<>"",VLOOKUP(AM1311,Selects!$M$4:$N$1000,2,0),"") | BB1311: =IF(BA1311<>"",VLOOKUP(BA1311,Selects!$B$4:$C$100,2,0),"") | BG1311: =IF(LEN(BF1311)=11,"PF",IF(LEN(BF1311)=14,"PJ","")) | BI1311: =IF(BH1311<>"",VLOOKUP(BH1311,Selects!$G:$H,2,0),"") | BO1311: =IF(BN1311<>"",VLOOKUP(BN1311,Selects!$J$4:$K$1000,2,0),"") | CB1311: =IF(AC1311<>"",VLOOKUP(AC1311,Selects!$B:$E,4,0),"")
E1312: =IF(LEN(D1312)=11,"PF",IF(LEN(D1312)=14,"PJ","")) | H1312: =IF(G1312<>"",VLOOKUP(G1312,'Cnae mcc id'!$A:$M,9,0),"") | J1312: =IF(I1312<>"",VLOOKUP(I1312,'Legal Nature'!$E$2:$G$84,3,0),"") | U1312: =IF( T1312<>"",VLOOKUP(T1312,Selects!$M$4:$N$1000,2,0),"") | AD1312: =IF(AC1312<>"",VLOOKUP(AC1312,Selects!$B$4:$C$100,2,0),"") | AM1312: =IF(LEFT(AL1312,1)="9","Celular",IF(AL1312="","","Fixo")) | AN1312: =IF( AM1312<>"",VLOOKUP(AM1312,Selects!$M$4:$N$1000,2,0),"") | BB1312: =IF(BA1312<>"",VLOOKUP(BA1312,Selects!$B$4:$C$100,2,0),"") | BG1312: =IF(LEN(BF1312)=11,"PF",IF(LEN(BF1312)=14,"PJ","")) | BI1312: =IF(BH1312<>"",VLOOKUP(BH1312,Selects!$G:$H,2,0),"") | BO1312: =IF(BN1312<>"",VLOOKUP(BN1312,Selects!$J$4:$K$1000,2,0),"") | CB1312: =IF(AC1312<>"",VLOOKUP(AC1312,Selects!$B:$E,4,0),"")
E1313: =IF(LEN(D1313)=11,"PF",IF(LEN(D1313)=14,"PJ","")) | H1313: =IF(G1313<>"",VLOOKUP(G1313,'Cnae mcc id'!$A:$M,9,0),"") | J1313: =IF(I1313<>"",VLOOKUP(I1313,'Legal Nature'!$E$2:$G$84,3,0),"") | U1313: =IF( T1313<>"",VLOOKUP(T1313,Selects!$M$4:$N$1000,2,0),"") | AD1313: =IF(AC1313<>"",VLOOKUP(AC1313,Selects!$B$4:$C$100,2,0),"") | AM1313: =IF(LEFT(AL1313,1)="9","Celular",IF(AL1313="","","Fixo")) | AN1313: =IF( AM1313<>"",VLOOKUP(AM1313,Selects!$M$4:$N$1000,2,0),"") | BB1313: =IF(BA1313<>"",VLOOKUP(BA1313,Selects!$B$4:$C$100,2,0),"") | BG1313: =IF(LEN(BF1313)=11,"PF",IF(LEN(BF1313)=14,"PJ","")) | BI1313: =IF(BH1313<>"",VLOOKUP(BH1313,Selects!$G:$H,2,0),"") | BO1313: =IF(BN1313<>"",VLOOKUP(BN1313,Selects!$J$4:$K$1000,2,0),"") | CB1313: =IF(AC1313<>"",VLOOKUP(AC1313,Selects!$B:$E,4,0),"")
E1314: =IF(LEN(D1314)=11,"PF",IF(LEN(D1314)=14,"PJ","")) | H1314: =IF(G1314<>"",VLOOKUP(G1314,'Cnae mcc id'!$A:$M,9,0),"") | J1314: =IF(I1314<>"",VLOOKUP(I1314,'Legal Nature'!$E$2:$G$84,3,0),"") | U1314: =IF( T1314<>"",VLOOKUP(T1314,Selects!$M$4:$N$1000,2,0),"") | AD1314: =IF(AC1314<>"",VLOOKUP(AC1314,Selects!$B$4:$C$100,2,0),"") | AM1314: =IF(LEFT(AL1314,1)="9","Celular",IF(AL1314="","","Fixo")) | AN1314: =IF( AM1314<>"",VLOOKUP(AM1314,Selects!$M$4:$N$1000,2,0),"") | BB1314: =IF(BA1314<>"",VLOOKUP(BA1314,Selects!$B$4:$C$100,2,0),"") | BG1314: =IF(LEN(BF1314)=11,"PF",IF(LEN(BF1314)=14,"PJ","")) | BI1314: =IF(BH1314<>"",VLOOKUP(BH1314,Selects!$G:$H,2,0),"") | BO1314: =IF(BN1314<>"",VLOOKUP(BN1314,Selects!$J$4:$K$1000,2,0),"") | CB1314: =IF(AC1314<>"",VLOOKUP(AC1314,Selects!$B:$E,4,0),"")
E1315: =IF(LEN(D1315)=11,"PF",IF(LEN(D1315)=14,"PJ","")) | H1315: =IF(G1315<>"",VLOOKUP(G1315,'Cnae mcc id'!$A:$M,9,0),"") | J1315: =IF(I1315<>"",VLOOKUP(I1315,'Legal Nature'!$E$2:$G$84,3,0),"") | U1315: =IF( T1315<>"",VLOOKUP(T1315,Selects!$M$4:$N$1000,2,0),"") | AD1315: =IF(AC1315<>"",VLOOKUP(AC1315,Selects!$B$4:$C$100,2,0),"") | AM1315: =IF(LEFT(AL1315,1)="9","Celular",IF(AL1315="","","Fixo")) | AN1315: =IF( AM1315<>"",VLOOKUP(AM1315,Selects!$M$4:$N$1000,2,0),"") | BB1315: =IF(BA1315<>"",VLOOKUP(BA1315,Selects!$B$4:$C$100,2,0),"") | BG1315: =IF(LEN(BF1315)=11,"PF",IF(LEN(BF1315)=14,"PJ","")) | BI1315: =IF(BH1315<>"",VLOOKUP(BH1315,Selects!$G:$H,2,0),"") | BO1315: =IF(BN1315<>"",VLOOKUP(BN1315,Selects!$J$4:$K$1000,2,0),"") | CB1315: =IF(AC1315<>"",VLOOKUP(AC1315,Selects!$B:$E,4,0),"")
E1316: =IF(LEN(D1316)=11,"PF",IF(LEN(D1316)=14,"PJ","")) | H1316: =IF(G1316<>"",VLOOKUP(G1316,'Cnae mcc id'!$A:$M,9,0),"") | J1316: =IF(I1316<>"",VLOOKUP(I1316,'Legal Nature'!$E$2:$G$84,3,0),"") | U1316: =IF( T1316<>"",VLOOKUP(T1316,Selects!$M$4:$N$1000,2,0),"") | AD1316: =IF(AC1316<>"",VLOOKUP(AC1316,Selects!$B$4:$C$100,2,0),"") | AM1316: =IF(LEFT(AL1316,1)="9","Celular",IF(AL1316="","","Fixo")) | AN1316: =IF( AM1316<>"",VLOOKUP(AM1316,Selects!$M$4:$N$1000,2,0),"") | BB1316: =IF(BA1316<>"",VLOOKUP(BA1316,Selects!$B$4:$C$100,2,0),"") | BG1316: =IF(LEN(BF1316)=11,"PF",IF(LEN(BF1316)=14,"PJ","")) | BI1316: =IF(BH1316<>"",VLOOKUP(BH1316,Selects!$G:$H,2,0),"") | BO1316: =IF(BN1316<>"",VLOOKUP(BN1316,Selects!$J$4:$K$1000,2,0),"") | CB1316: =IF(AC1316<>"",VLOOKUP(AC1316,Selects!$B:$E,4,0),"")
E1317: =IF(LEN(D1317)=11,"PF",IF(LEN(D1317)=14,"PJ","")) | H1317: =IF(G1317<>"",VLOOKUP(G1317,'Cnae mcc id'!$A:$M,9,0),"") | J1317: =IF(I1317<>"",VLOOKUP(I1317,'Legal Nature'!$E$2:$G$84,3,0),"") | U1317: =IF( T1317<>"",VLOOKUP(T1317,Selects!$M$4:$N$1000,2,0),"") | AD1317: =IF(AC1317<>"",VLOOKUP(AC1317,Selects!$B$4:$C$100,2,0),"") | AM1317: =IF(LEFT(AL1317,1)="9","Celular",IF(AL1317="","","Fixo")) | AN1317: =IF( AM1317<>"",VLOOKUP(AM1317,Selects!$M$4:$N$1000,2,0),"") | BB1317: =IF(BA1317<>"",VLOOKUP(BA1317,Selects!$B$4:$C$100,2,0),"") | BG1317: =IF(LEN(BF1317)=11,"PF",IF(LEN(BF1317)=14,"PJ","")) | BI1317: =IF(BH1317<>"",VLOOKUP(BH1317,Selects!$G:$H,2,0),"") | BO1317: =IF(BN1317<>"",VLOOKUP(BN1317,Selects!$J$4:$K$1000,2,0),"") | CB1317: =IF(AC1317<>"",VLOOKUP(AC1317,Selects!$B:$E,4,0),"")
E1318: =IF(LEN(D1318)=11,"PF",IF(LEN(D1318)=14,"PJ","")) | H1318: =IF(G1318<>"",VLOOKUP(G1318,'Cnae mcc id'!$A:$M,9,0),"") | J1318: =IF(I1318<>"",VLOOKUP(I1318,'Legal Nature'!$E$2:$G$84,3,0),"") | U1318: =IF( T1318<>"",VLOOKUP(T1318,Selects!$M$4:$N$1000,2,0),"") | AD1318: =IF(AC1318<>"",VLOOKUP(AC1318,Selects!$B$4:$C$100,2,0),"") | AM1318: =IF(LEFT(AL1318,1)="9","Celular",IF(AL1318="","","Fixo")) | AN1318: =IF( AM1318<>"",VLOOKUP(AM1318,Selects!$M$4:$N$1000,2,0),"") | BB1318: =IF(BA1318<>"",VLOOKUP(BA1318,Selects!$B$4:$C$100,2,0),"") | BG1318: =IF(LEN(BF1318)=11,"PF",IF(LEN(BF1318)=14,"PJ","")) | BI1318: =IF(BH1318<>"",VLOOKUP(BH1318,Selects!$G:$H,2,0),"") | BO1318: =IF(BN1318<>"",VLOOKUP(BN1318,Selects!$J$4:$K$1000,2,0),"") | CB1318: =IF(AC1318<>"",VLOOKUP(AC1318,Selects!$B:$E,4,0),"")
E1319: =IF(LEN(D1319)=11,"PF",IF(LEN(D1319)=14,"PJ","")) | H1319: =IF(G1319<>"",VLOOKUP(G1319,'Cnae mcc id'!$A:$M,9,0),"") | J1319: =IF(I1319<>"",VLOOKUP(I1319,'Legal Nature'!$E$2:$G$84,3,0),"") | U1319: =IF( T1319<>"",VLOOKUP(T1319,Selects!$M$4:$N$1000,2,0),"") | AD1319: =IF(AC1319<>"",VLOOKUP(AC1319,Selects!$B$4:$C$100,2,0),"") | AM1319: =IF(LEFT(AL1319,1)="9","Celular",IF(AL1319="","","Fixo")) | AN1319: =IF( AM1319<>"",VLOOKUP(AM1319,Selects!$M$4:$N$1000,2,0),"") | BB1319: =IF(BA1319<>"",VLOOKUP(BA1319,Selects!$B$4:$C$100,2,0),"") | BG1319: =IF(LEN(BF1319)=11,"PF",IF(LEN(BF1319)=14,"PJ","")) | BI1319: =IF(BH1319<>"",VLOOKUP(BH1319,Selects!$G:$H,2,0),"") | BO1319: =IF(BN1319<>"",VLOOKUP(BN1319,Selects!$J$4:$K$1000,2,0),"") | CB1319: =IF(AC1319<>"",VLOOKUP(AC1319,Selects!$B:$E,4,0),"")
... E1395: =IF(LEN(D1395)=11,"PF",IF(LEN(D1395)=14,"PJ","")) | H1395: =IF(G1395<>"",VLOOKUP(G1395,'Cnae mcc id'!$A:$M,9,0),"") | J1395: =IF(I1395<>"",VLOOKUP(I1395,'Legal Nature'!$E$2:$G$84,3,0),"") | U1395: =IF( T1395<>"",VLOOKUP(T1395,Selects!$M$4:$N$1000,2,0),"") | AD1395: =IF(AC1395<>"",VLOOKUP(AC1395,Selects!$B$4:$C$100,2,0),"") | AM1395: =IF(LEFT(AL1395,1)="9","Celular",IF(AL1395="","","Fixo")) | AN1395: =IF( AM1395<>"",VLOOKUP(AM1395,Selects!$M$4:$N$1000,2,0),"") | BB1395: =IF(BA1395<>"",VLOOKUP(BA1395,Selects!$B$4:$C$100,2,0),"") | BG1395: =IF(LEN(BF1395)=11,"PF",IF(LEN(BF1395)=14,"PJ","")) | BI1395: =IF(BH1395<>"",VLOOKUP(BH1395,Selects!$G:$H,2,0),"") | BO1395: =IF(BN1395<>"",VLOOKUP(BN1395,Selects!$J$4:$K$1000,2,0),"") | CB1395: =IF(AC1395<>"",VLOOKUP(AC1395,Selects!$B:$E,4,0),"")
E1396: =IF(LEN(D1396)=11,"PF",IF(LEN(D1396)=14,"PJ","")) | H1396: =IF(G1396<>"",VLOOKUP(G1396,'Cnae mcc id'!$A:$M,9,0),"") | J1396: =IF(I1396<>"",VLOOKUP(I1396,'Legal Nature'!$E$2:$G$84,3,0),"") | U1396: =IF( T1396<>"",VLOOKUP(T1396,Selects!$M$4:$N$1000,2,0),"") | AD1396: =IF(AC1396<>"",VLOOKUP(AC1396,Selects!$B$4:$C$100,2,0),"") | AM1396: =IF(LEFT(AL1396,1)="9","Celular",IF(AL1396="","","Fixo")) | AN1396: =IF( AM1396<>"",VLOOKUP(AM1396,Selects!$M$4:$N$1000,2,0),"") | BB1396: =IF(BA1396<>"",VLOOKUP(BA1396,Selects!$B$4:$C$100,2,0),"") | BG1396: =IF(LEN(BF1396)=11,"PF",IF(LEN(BF1396)=14,"PJ","")) | BI1396: =IF(BH1396<>"",VLOOKUP(BH1396,Selects!$G:$H,2,0),"") | CB1396: =IF(AC1396<>"",VLOOKUP(AC1396,Selects!$B:$E,4,0),"")
E1397: =IF(LEN(D1397)=11,"PF",IF(LEN(D1397)=14,"PJ","")) | H1397: =IF(G1397<>"",VLOOKUP(G1397,'Cnae mcc id'!$A:$M,9,0),"") | J1397: =IF(I1397<>"",VLOOKUP(I1397,'Legal Nature'!$E$2:$G$84,3,0),"") | U1397: =IF( T1397<>"",VLOOKUP(T1397,Selects!$M$4:$N$1000,2,0),"") | AD1397: =IF(AC1397<>"",VLOOKUP(AC1397,Selects!$B$4:$C$100,2,0),"") | AM1397: =IF(LEFT(AL1397,1)="9","Celular",IF(AL1397="","","Fixo")) | AN1397: =IF( AM1397<>"",VLOOKUP(AM1397,Selects!$M$4:$N$1000,2,0),"") | BB1397: =IF(BA1397<>"",VLOOKUP(BA1397,Selects!$B$4:$C$100,2,0),"") | BG1397: =IF(LEN(BF1397)=11,"PF",IF(LEN(BF1397)=14,"PJ","")) | BI1397: =IF(BH1397<>"",VLOOKUP(BH1397,Selects!$G:$H,2,0),"") | CB1397: =IF(AC1397<>"",VLOOKUP(AC1397,Selects!$B:$E,4,0),"")
E1398: =IF(LEN(D1398)=11,"PF",IF(LEN(D1398)=14,"PJ","")) | H1398: =IF(G1398<>"",VLOOKUP(G1398,'Cnae mcc id'!$A:$M,9,0),"") | J1398: =IF(I1398<>"",VLOOKUP(I1398,'Legal Nature'!$E$2:$G$84,3,0),"") | U1398: =IF( T1398<>"",VLOOKUP(T1398,Selects!$M$4:$N$1000,2,0),"") | AD1398: =IF(AC1398<>"",VLOOKUP(AC1398,Selects!$B$4:$C$100,2,0),"") | AM1398: =IF(LEFT(AL1398,1)="9","Celular",IF(AL1398="","","Fixo")) | AN1398: =IF( AM1398<>"",VLOOKUP(AM1398,Selects!$M$4:$N$1000,2,0),"") | BB1398: =IF(BA1398<>"",VLOOKUP(BA1398,Selects!$B$4:$C$100,2,0),"") | BG1398: =IF(LEN(BF1398)=11,"PF",IF(LEN(BF1398)=14,"PJ","")) | BI1398: =IF(BH1398<>"",VLOOKUP(BH1398,Selects!$G:$H,2,0),"") | CB1398: =IF(AC1398<>"",VLOOKUP(AC1398,Selects!$B:$E,4,0),"")
E1399: =IF(LEN(D1399)=11,"PF",IF(LEN(D1399)=14,"PJ","")) | H1399: =IF(G1399<>"",VLOOKUP(G1399,'Cnae mcc id'!$A:$M,9,0),"") | J1399: =IF(I1399<>"",VLOOKUP(I1399,'Legal Nature'!$E$2:$G$84,3,0),"") | U1399: =IF( T1399<>"",VLOOKUP(T1399,Selects!$M$4:$N$1000,2,0),"") | AD1399: =IF(AC1399<>"",VLOOKUP(AC1399,Selects!$B$4:$C$100,2,0),"") | AM1399: =IF(LEFT(AL1399,1)="9","Celular",IF(AL1399="","","Fixo")) | AN1399: =IF( AM1399<>"",VLOOKUP(AM1399,Selects!$M$4:$N$1000,2,0),"") | BB1399: =IF(BA1399<>"",VLOOKUP(BA1399,Selects!$B$4:$C$100,2,0),"") | BG1399: =IF(LEN(BF1399)=11,"PF",IF(LEN(BF1399)=14,"PJ","")) | BI1399: =IF(BH1399<>"",VLOOKUP(BH1399,Selects!$G:$H,2,0),"") | CB1399: =IF(AC1399<>"",VLOOKUP(AC1399,Selects!$B:$E,4,0),"")
E1400: =IF(LEN(D1400)=11,"PF",IF(LEN(D1400)=14,"PJ","")) | H1400: =IF(G1400<>"",VLOOKUP(G1400,'Cnae mcc id'!$A:$M,9,0),"") | J1400: =IF(I1400<>"",VLOOKUP(I1400,'Legal Nature'!$E$2:$G$84,3,0),"") | U1400: =IF( T1400<>"",VLOOKUP(T1400,Selects!$M$4:$N$1000,2,0),"") | AD1400: =IF(AC1400<>"",VLOOKUP(AC1400,Selects!$B$4:$C$100,2,0),"") | AM1400: =IF(LEFT(AL1400,1)="9","Celular",IF(AL1400="","","Fixo")) | AN1400: =IF( AM1400<>"",VLOOKUP(AM1400,Selects!$M$4:$N$1000,2,0),"") | BB1400: =IF(BA1400<>"",VLOOKUP(BA1400,Selects!$B$4:$C$100,2,0),"") | BG1400: =IF(LEN(BF1400)=11,"PF",IF(LEN(BF1400)=14,"PJ","")) | BI1400: =IF(BH1400<>"",VLOOKUP(BH1400,Selects!$G:$H,2,0),"") | CB1400: =IF(AC1400<>"",VLOOKUP(AC1400,Selects!$B:$E,4,0),"")
E1401: =IF(LEN(D1401)=11,"PF",IF(LEN(D1401)=14,"PJ","")) | H1401: =IF(G1401<>"",VLOOKUP(G1401,'Cnae mcc id'!$A:$M,9,0),"") | J1401: =IF(I1401<>"",VLOOKUP(I1401,'Legal Nature'!$E$2:$G$84,3,0),"") | U1401: =IF( T1401<>"",VLOOKUP(T1401,Selects!$M$4:$N$1000,2,0),"") | AD1401: =IF(AC1401<>"",VLOOKUP(AC1401,Selects!$B$4:$C$100,2,0),"") | AM1401: =IF(LEFT(AL1401,1)="9","Celular",IF(AL1401="","","Fixo")) | AN1401: =IF( AM1401<>"",VLOOKUP(AM1401,Selects!$M$4:$N$1000,2,0),"") | BB1401: =IF(BA1401<>"",VLOOKUP(BA1401,Selects!$B$4:$C$100,2,0),"") | BG1401: =IF(LEN(BF1401)=11,"PF",IF(LEN(BF1401)=14,"PJ","")) | BI1401: =IF(BH1401<>"",VLOOKUP(BH1401,Selects!$G:$H,2,0),"") | CB1401: =IF(AC1401<>"",VLOOKUP(AC1401,Selects!$B:$E,4,0),"")
E1402: =IF(LEN(D1402)=11,"PF",IF(LEN(D1402)=14,"PJ","")) | H1402: =IF(G1402<>"",VLOOKUP(G1402,'Cnae mcc id'!$A:$M,9,0),"") | J1402: =IF(I1402<>"",VLOOKUP(I1402,'Legal Nature'!$E$2:$G$84,3,0),"") | U1402: =IF( T1402<>"",VLOOKUP(T1402,Selects!$M$4:$N$1000,2,0),"") | AD1402: =IF(AC1402<>"",VLOOKUP(AC1402,Selects!$B$4:$C$100,2,0),"") | AM1402: =IF(LEFT(AL1402,1)="9","Celular",IF(AL1402="","","Fixo")) | AN1402: =IF( AM1402<>"",VLOOKUP(AM1402,Selects!$M$4:$N$1000,2,0),"") | BB1402: =IF(BA1402<>"",VLOOKUP(BA1402,Selects!$B$4:$C$100,2,0),"") | BG1402: =IF(LEN(BF1402)=11,"PF",IF(LEN(BF1402)=14,"PJ","")) | BI1402: =IF(BH1402<>"",VLOOKUP(BH1402,Selects!$G:$H,2,0),"") | CB1402: =IF(AC1402<>"",VLOOKUP(AC1402,Selects!$B:$E,4,0),"")
E1403: =IF(LEN(D1403)=11,"PF",IF(LEN(D1403)=14,"PJ","")) | H1403: =IF(G1403<>"",VLOOKUP(G1403,'Cnae mcc id'!$A:$M,9,0),"") | J1403: =IF(I1403<>"",VLOOKUP(I1403,'Legal Nature'!$E$2:$G$84,3,0),"") | U1403: =IF( T1403<>"",VLOOKUP(T1403,Selects!$M$4:$N$1000,2,0),"") | AD1403: =IF(AC1403<>"",VLOOKUP(AC1403,Selects!$B$4:$C$100,2,0),"") | AM1403: =IF(LEFT(AL1403,1)="9","Celular",IF(AL1403="","","Fixo")) | AN1403: =IF( AM1403<>"",VLOOKUP(AM1403,Selects!$M$4:$N$1000,2,0),"") | BB1403: =IF(BA1403<>"",VLOOKUP(BA1403,Selects!$B$4:$C$100,2,0),"") | BG1403: =IF(LEN(BF1403)=11,"PF",IF(LEN(BF1403)=14,"PJ","")) | BI1403: =IF(BH1403<>"",VLOOKUP(BH1403,Selects!$G:$H,2,0),"") | CB1403: =IF(AC1403<>"",VLOOKUP(AC1403,Selects!$B:$E,4,0),"")
E1404: =IF(LEN(D1404)=11,"PF",IF(LEN(D1404)=14,"PJ","")) | H1404: =IF(G1404<>"",VLOOKUP(G1404,'Cnae mcc id'!$A:$M,9,0),"") | J1404: =IF(I1404<>"",VLOOKUP(I1404,'Legal Nature'!$E$2:$G$84,3,0),"") | U1404: =IF( T1404<>"",VLOOKUP(T1404,Selects!$M$4:$N$1000,2,0),"") | AD1404: =IF(AC1404<>"",VLOOKUP(AC1404,Selects!$B$4:$C$100,2,0),"") | AM1404: =IF(LEFT(AL1404,1)="9","Celular",IF(AL1404="","","Fixo")) | AN1404: =IF( AM1404<>"",VLOOKUP(AM1404,Selects!$M$4:$N$1000,2,0),"") | BB1404: =IF(BA1404<>"",VLOOKUP(BA1404,Selects!$B$4:$C$100,2,0),"") | BG1404: =IF(LEN(BF1404)=11,"PF",IF(LEN(BF1404)=14,"PJ","")) | BI1404: =IF(BH1404<>"",VLOOKUP(BH1404,Selects!$G:$H,2,0),"") | CB1404: =IF(AC1404<>"",VLOOKUP(AC1404,Selects!$B:$E,4,0),"")
E1405: =IF(LEN(D1405)=11,"PF",IF(LEN(D1405)=14,"PJ","")) | H1405: =IF(G1405<>"",VLOOKUP(G1405,'Cnae mcc id'!$A:$M,9,0),"") | J1405: =IF(I1405<>"",VLOOKUP(I1405,'Legal Nature'!$E$2:$G$84,3,0),"") | U1405: =IF( T1405<>"",VLOOKUP(T1405,Selects!$M$4:$N$1000,2,0),"") | AD1405: =IF(AC1405<>"",VLOOKUP(AC1405,Selects!$B$4:$C$100,2,0),"") | AM1405: =IF(LEFT(AL1405,1)="9","Celular",IF(AL1405="","","Fixo")) | AN1405: =IF( AM1405<>"",VLOOKUP(AM1405,Selects!$M$4:$N$1000,2,0),"") | BB1405: =IF(BA1405<>"",VLOOKUP(BA1405,Selects!$B$4:$C$100,2,0),"") | BG1405: =IF(LEN(BF1405)=11,"PF",IF(LEN(BF1405)=14,"PJ","")) | BI1405: =IF(BH1405<>"",VLOOKUP(BH1405,Selects!$G:$H,2,0),"") | CB1405: =IF(AC1405<>"",VLOOKUP(AC1405,Selects!$B:$E,4,0),"")
E1406: =IF(LEN(D1406)=11,"PF",IF(LEN(D1406)=14,"PJ","")) | H1406: =IF(G1406<>"",VLOOKUP(G1406,'Cnae mcc id'!$A:$M,9,0),"") | J1406: =IF(I1406<>"",VLOOKUP(I1406,'Legal Nature'!$E$2:$G$84,3,0),"") | U1406: =IF( T1406<>"",VLOOKUP(T1406,Selects!$M$4:$N$1000,2,0),"") | AD1406: =IF(AC1406<>"",VLOOKUP(AC1406,Selects!$B$4:$C$100,2,0),"") | AM1406: =IF(LEFT(AL1406,1)="9","Celular",IF(AL1406="","","Fixo")) | AN1406: =IF( AM1406<>"",VLOOKUP(AM1406,Selects!$M$4:$N$1000,2,0),"") | BB1406: =IF(BA1406<>"",VLOOKUP(BA1406,Selects!$B$4:$C$100,2,0),"") | BG1406: =IF(LEN(BF1406)=11,"PF",IF(LEN(BF1406)=14,"PJ","")) | BI1406: =IF(BH1406<>"",VLOOKUP(BH1406,Selects!$G:$H,2,0),"") | CB1406: =IF(AC1406<>"",VLOOKUP(AC1406,Selects!$B:$E,4,0),"")
E1407: =IF(LEN(D1407)=11,"PF",IF(LEN(D1407)=14,"PJ","")) | H1407: =IF(G1407<>"",VLOOKUP(G1407,'Cnae mcc id'!$A:$M,9,0),"") | J1407: =IF(I1407<>"",VLOOKUP(I1407,'Legal Nature'!$E$2:$G$84,3,0),"") | U1407: =IF( T1407<>"",VLOOKUP(T1407,Selects!$M$4:$N$1000,2,0),"") | AD1407: =IF(AC1407<>"",VLOOKUP(AC1407,Selects!$B$4:$C$100,2,0),"") | AM1407: =IF(LEFT(AL1407,1)="9","Celular",IF(AL1407="","","Fixo")) | AN1407: =IF( AM1407<>"",VLOOKUP(AM1407,Selects!$M$4:$N$1000,2,0),"") | BB1407: =IF(BA1407<>"",VLOOKUP(BA1407,Selects!$B$4:$C$100,2,0),"") | BG1407: =IF(LEN(BF1407)=11,"PF",IF(LEN(BF1407)=14,"PJ","")) | BI1407: =IF(BH1407<>"",VLOOKUP(BH1407,Selects!$G:$H,2,0),"") | CB1407: =IF(AC1407<>"",VLOOKUP(AC1407,Selects!$B:$E,4,0),"")
... E1413: =IF(LEN(D1413)=11,"PF",IF(LEN(D1413)=14,"PJ","")) | H1413: =IF(G1413<>"",VLOOKUP(G1413,'Cnae mcc id'!$A:$M,9,0),"") | J1413: =IF(I1413<>"",VLOOKUP(I1413,'Legal Nature'!$E$2:$G$84,3,0),"") | U1413: =IF( T1413<>"",VLOOKUP(T1413,Selects!$M$4:$N$1000,2,0),"") | AD1413: =IF(AC1413<>"",VLOOKUP(AC1413,Selects!$B$4:$C$100,2,0),"") | AM1413: =IF(LEFT(AL1413,1)="9","Celular",IF(AL1413="","","Fixo")) | AN1413: =IF( AM1413<>"",VLOOKUP(AM1413,Selects!$M$4:$N$1000,2,0),"") | BB1413: =IF(BA1413<>"",VLOOKUP(BA1413,Selects!$B$4:$C$100,2,0),"") | BG1413: =IF(LEN(BF1413)=11,"PF",IF(LEN(BF1413)=14,"PJ","")) | BI1413: =IF(BH1413<>"",VLOOKUP(BH1413,Selects!$G:$H,2,0),"") | CB1413: =IF(AC1413<>"",VLOOKUP(AC1413,Selects!$B:$E,4,0),"")
E1414: =IF(LEN(D1414)=11,"PF",IF(LEN(D1414)=14,"PJ","")) | J1414: =IF(I1414<>"",VLOOKUP(I1414,'Legal Nature'!$E$2:$G$84,3,0),"") | U1414: =IF( T1414<>"",VLOOKUP(T1414,Selects!$M$4:$N$1000,2,0),"") | AD1414: =IF(AC1414<>"",VLOOKUP(AC1414,Selects!$B$4:$C$100,2,0),"") | AM1414: =IF(LEFT(AL1414,1)="9","Celular",IF(AL1414="","","Fixo")) | AN1414: =IF( AM1414<>"",VLOOKUP(AM1414,Selects!$M$4:$N$1000,2,0),"") | BB1414: =IF(BA1414<>"",VLOOKUP(BA1414,Selects!$B$4:$C$100,2,0),"") | BG1414: =IF(LEN(BF1414)=11,"PF",IF(LEN(BF1414)=14,"PJ","")) | BI1414: =IF(BH1414<>"",VLOOKUP(BH1414,Selects!$G:$H,2,0),"") | CB1414: =IF(AC1414<>"",VLOOKUP(AC1414,Selects!$B:$E,4,0),"")
E1415: =IF(LEN(D1415)=11,"PF",IF(LEN(D1415)=14,"PJ","")) | J1415: =IF(I1415<>"",VLOOKUP(I1415,'Legal Nature'!$E$2:$G$84,3,0),"") | U1415: =IF( T1415<>"",VLOOKUP(T1415,Selects!$M$4:$N$1000,2,0),"") | AD1415: =IF(AC1415<>"",VLOOKUP(AC1415,Selects!$B$4:$C$100,2,0),"") | AM1415: =IF(LEFT(AL1415,1)="9","Celular",IF(AL1415="","","Fixo")) | AN1415: =IF( AM1415<>"",VLOOKUP(AM1415,Selects!$M$4:$N$1000,2,0),"") | BB1415: =IF(BA1415<>"",VLOOKUP(BA1415,Selects!$B$4:$C$100,2,0),"") | BG1415: =IF(LEN(BF1415)=11,"PF",IF(LEN(BF1415)=14,"PJ","")) | BI1415: =IF(BH1415<>"",VLOOKUP(BH1415,Selects!$G:$H,2,0),"") | CB1415: =IF(AC1415<>"",VLOOKUP(AC1415,Selects!$B:$E,4,0),"")
E1416: =IF(LEN(D1416)=11,"PF",IF(LEN(D1416)=14,"PJ","")) | J1416: =IF(I1416<>"",VLOOKUP(I1416,'Legal Nature'!$E$2:$G$84,3,0),"") | U1416: =IF( T1416<>"",VLOOKUP(T1416,Selects!$M$4:$N$1000,2,0),"") | AD1416: =IF(AC1416<>"",VLOOKUP(AC1416,Selects!$B$4:$C$100,2,0),"") | AM1416: =IF(LEFT(AL1416,1)="9","Celular",IF(AL1416="","","Fixo")) | AN1416: =IF( AM1416<>"",VLOOKUP(AM1416,Selects!$M$4:$N$1000,2,0),"") | BB1416: =IF(BA1416<>"",VLOOKUP(BA1416,Selects!$B$4:$C$100,2,0),"") | BG1416: =IF(LEN(BF1416)=11,"PF",IF(LEN(BF1416)=14,"PJ","")) | BI1416: =IF(BH1416<>"",VLOOKUP(BH1416,Selects!$G:$H,2,0),"") | CB1416: =IF(AC1416<>"",VLOOKUP(AC1416,Selects!$B:$E,4,0),"")
E1417: =IF(LEN(D1417)=11,"PF",IF(LEN(D1417)=14,"PJ","")) | J1417: =IF(I1417<>"",VLOOKUP(I1417,'Legal Nature'!$E$2:$G$84,3,0),"") | U1417: =IF( T1417<>"",VLOOKUP(T1417,Selects!$M$4:$N$1000,2,0),"") | AD1417: =IF(AC1417<>"",VLOOKUP(AC1417,Selects!$B$4:$C$100,2,0),"") | AM1417: =IF(LEFT(AL1417,1)="9","Celular",IF(AL1417="","","Fixo")) | AN1417: =IF( AM1417<>"",VLOOKUP(AM1417,Selects!$M$4:$N$1000,2,0),"") | BB1417: =IF(BA1417<>"",VLOOKUP(BA1417,Selects!$B$4:$C$100,2,0),"") | BG1417: =IF(LEN(BF1417)=11,"PF",IF(LEN(BF1417)=14,"PJ","")) | BI1417: =IF(BH1417<>"",VLOOKUP(BH1417,Selects!$G:$H,2,0),"") | CB1417: =IF(AC1417<>"",VLOOKUP(AC1417,Selects!$B:$E,4,0),"")
E1418: =IF(LEN(D1418)=11,"PF",IF(LEN(D1418)=14,"PJ","")) | J1418: =IF(I1418<>"",VLOOKUP(I1418,'Legal Nature'!$E$2:$G$84,3,0),"") | U1418: =IF( T1418<>"",VLOOKUP(T1418,Selects!$M$4:$N$1000,2,0),"") | AD1418: =IF(AC1418<>"",VLOOKUP(AC1418,Selects!$B$4:$C$100,2,0),"") | AM1418: =IF(LEFT(AL1418,1)="9","Celular",IF(AL1418="","","Fixo")) | AN1418: =IF( AM1418<>"",VLOOKUP(AM1418,Selects!$M$4:$N$1000,2,0),"") | BB1418: =IF(BA1418<>"",VLOOKUP(BA1418,Selects!$B$4:$C$100,2,0),"") | BG1418: =IF(LEN(BF1418)=11,"PF",IF(LEN(BF1418)=14,"PJ","")) | BI1418: =IF(BH1418<>"",VLOOKUP(BH1418,Selects!$G:$H,2,0),"") | CB1418: =IF(AC1418<>"",VLOOKUP(AC1418,Selects!$B:$E,4,0),"")
E1419: =IF(LEN(D1419)=11,"PF",IF(LEN(D1419)=14,"PJ","")) | J1419: =IF(I1419<>"",VLOOKUP(I1419,'Legal Nature'!$E$2:$G$84,3,0),"") | U1419: =IF( T1419<>"",VLOOKUP(T1419,Selects!$M$4:$N$1000,2,0),"") | AD1419: =IF(AC1419<>"",VLOOKUP(AC1419,Selects!$B$4:$C$100,2,0),"") | AM1419: =IF(LEFT(AL1419,1)="9","Celular",IF(AL1419="","","Fixo")) | AN1419: =IF( AM1419<>"",VLOOKUP(AM1419,Selects!$M$4:$N$1000,2,0),"") | BB1419: =IF(BA1419<>"",VLOOKUP(BA1419,Selects!$B$4:$C$100,2,0),"") | BG1419: =IF(LEN(BF1419)=11,"PF",IF(LEN(BF1419)=14,"PJ","")) | BI1419: =IF(BH1419<>"",VLOOKUP(BH1419,Selects!$G:$H,2,0),"") | CB1419: =IF(AC1419<>"",VLOOKUP(AC1419,Selects!$B:$E,4,0),"")
E1420: =IF(LEN(D1420)=11,"PF",IF(LEN(D1420)=14,"PJ","")) | J1420: =IF(I1420<>"",VLOOKUP(I1420,'Legal Nature'!$E$2:$G$84,3,0),"") | U1420: =IF( T1420<>"",VLOOKUP(T1420,Selects!$M$4:$N$1000,2,0),"") | AD1420: =IF(AC1420<>"",VLOOKUP(AC1420,Selects!$B$4:$C$100,2,0),"") | AM1420: =IF(LEFT(AL1420,1)="9","Celular",IF(AL1420="","","Fixo")) | AN1420: =IF( AM1420<>"",VLOOKUP(AM1420,Selects!$M$4:$N$1000,2,0),"") | BB1420: =IF(BA1420<>"",VLOOKUP(BA1420,Selects!$B$4:$C$100,2,0),"") | BG1420: =IF(LEN(BF1420)=11,"PF",IF(LEN(BF1420)=14,"PJ","")) | BI1420: =IF(BH1420<>"",VLOOKUP(BH1420,Selects!$G:$H,2,0),"") | CB1420: =IF(AC1420<>"",VLOOKUP(AC1420,Selects!$B:$E,4,0),"")
E1421: =IF(LEN(D1421)=11,"PF",IF(LEN(D1421)=14,"PJ","")) | J1421: =IF(I1421<>"",VLOOKUP(I1421,'Legal Nature'!$E$2:$G$84,3,0),"") | U1421: =IF( T1421<>"",VLOOKUP(T1421,Selects!$M$4:$N$1000,2,0),"") | AD1421: =IF(AC1421<>"",VLOOKUP(AC1421,Selects!$B$4:$C$100,2,0),"") | AM1421: =IF(LEFT(AL1421,1)="9","Celular",IF(AL1421="","","Fixo")) | AN1421: =IF( AM1421<>"",VLOOKUP(AM1421,Selects!$M$4:$N$1000,2,0),"") | BB1421: =IF(BA1421<>"",VLOOKUP(BA1421,Selects!$B$4:$C$100,2,0),"") | BG1421: =IF(LEN(BF1421)=11,"PF",IF(LEN(BF1421)=14,"PJ","")) | BI1421: =IF(BH1421<>"",VLOOKUP(BH1421,Selects!$G:$H,2,0),"") | CB1421: =IF(AC1421<>"",VLOOKUP(AC1421,Selects!$B:$E,4,0),"")
E1422: =IF(LEN(D1422)=11,"PF",IF(LEN(D1422)=14,"PJ","")) | J1422: =IF(I1422<>"",VLOOKUP(I1422,'Legal Nature'!$E$2:$G$84,3,0),"") | U1422: =IF( T1422<>"",VLOOKUP(T1422,Selects!$M$4:$N$1000,2,0),"") | AD1422: =IF(AC1422<>"",VLOOKUP(AC1422,Selects!$B$4:$C$100,2,0),"") | AM1422: =IF(LEFT(AL1422,1)="9","Celular",IF(AL1422="","","Fixo")) | AN1422: =IF( AM1422<>"",VLOOKUP(AM1422,Selects!$M$4:$N$1000,2,0),"") | BB1422: =IF(BA1422<>"",VLOOKUP(BA1422,Selects!$B$4:$C$100,2,0),"") | BG1422: =IF(LEN(BF1422)=11,"PF",IF(LEN(BF1422)=14,"PJ","")) | BI1422: =IF(BH1422<>"",VLOOKUP(BH1422,Selects!$G:$H,2,0),"") | CB1422: =IF(AC1422<>"",VLOOKUP(AC1422,Selects!$B:$E,4,0),"")
E1423: =IF(LEN(D1423)=11,"PF",IF(LEN(D1423)=14,"PJ","")) | J1423: =IF(I1423<>"",VLOOKUP(I1423,'Legal Nature'!$E$2:$G$84,3,0),"") | U1423: =IF( T1423<>"",VLOOKUP(T1423,Selects!$M$4:$N$1000,2,0),"") | AD1423: =IF(AC1423<>"",VLOOKUP(AC1423,Selects!$B$4:$C$100,2,0),"") | AM1423: =IF(LEFT(AL1423,1)="9","Celular",IF(AL1423="","","Fixo")) | AN1423: =IF( AM1423<>"",VLOOKUP(AM1423,Selects!$M$4:$N$1000,2,0),"") | BB1423: =IF(BA1423<>"",VLOOKUP(BA1423,Selects!$B$4:$C$100,2,0),"") | BG1423: =IF(LEN(BF1423)=11,"PF",IF(LEN(BF1423)=14,"PJ","")) | BI1423: =IF(BH1423<>"",VLOOKUP(BH1423,Selects!$G:$H,2,0),"") | CB1423: =IF(AC1423<>"",VLOOKUP(AC1423,Selects!$B:$E,4,0),"")
E1424: =IF(LEN(D1424)=11,"PF",IF(LEN(D1424)=14,"PJ","")) | J1424: =IF(I1424<>"",VLOOKUP(I1424,'Legal Nature'!$E$2:$G$84,3,0),"") | U1424: =IF( T1424<>"",VLOOKUP(T1424,Selects!$M$4:$N$1000,2,0),"") | AD1424: =IF(AC1424<>"",VLOOKUP(AC1424,Selects!$B$4:$C$100,2,0),"") | AM1424: =IF(LEFT(AL1424,1)="9","Celular",IF(AL1424="","","Fixo")) | AN1424: =IF( AM1424<>"",VLOOKUP(AM1424,Selects!$M$4:$N$1000,2,0),"") | BB1424: =IF(BA1424<>"",VLOOKUP(BA1424,Selects!$B$4:$C$100,2,0),"") | BG1424: =IF(LEN(BF1424)=11,"PF",IF(LEN(BF1424)=14,"PJ","")) | BI1424: =IF(BH1424<>"",VLOOKUP(BH1424,Selects!$G:$H,2,0),"") | CB1424: =IF(AC1424<>"",VLOOKUP(AC1424,Selects!$B:$E,4,0),"")
E1425: =IF(LEN(D1425)=11,"PF",IF(LEN(D1425)=14,"PJ","")) | J1425: =IF(I1425<>"",VLOOKUP(I1425,'Legal Nature'!$E$2:$G$84,3,0),"") | U1425: =IF( T1425<>"",VLOOKUP(T1425,Selects!$M$4:$N$1000,2,0),"") | AD1425: =IF(AC1425<>"",VLOOKUP(AC1425,Selects!$B$4:$C$100,2,0),"") | AM1425: =IF(LEFT(AL1425,1)="9","Celular",IF(AL1425="","","Fixo")) | AN1425: =IF( AM1425<>"",VLOOKUP(AM1425,Selects!$M$4:$N$1000,2,0),"") | BB1425: =IF(BA1425<>"",VLOOKUP(BA1425,Selects!$B$4:$C$100,2,0),"") | BG1425: =IF(LEN(BF1425)=11,"PF",IF(LEN(BF1425)=14,"PJ","")) | BI1425: =IF(BH1425<>"",VLOOKUP(BH1425,Selects!$G:$H,2,0),"") | CB1425: =IF(AC1425<>"",VLOOKUP(AC1425,Selects!$B:$E,4,0),"")
... E1706: =IF(LEN(D1706)=11,"PF",IF(LEN(D1706)=14,"PJ","")) | J1706: =IF(I1706<>"",VLOOKUP(I1706,'Legal Nature'!$E$2:$G$84,3,0),"") | U1706: =IF( T1706<>"",VLOOKUP(T1706,Selects!$M$4:$N$1000,2,0),"") | AD1706: =IF(AC1706<>"",VLOOKUP(AC1706,Selects!$B$4:$C$100,2,0),"") | AM1706: =IF(LEFT(AL1706,1)="9","Celular",IF(AL1706="","","Fixo")) | AN1706: =IF( AM1706<>"",VLOOKUP(AM1706,Selects!$M$4:$N$1000,2,0),"") | BB1706: =IF(BA1706<>"",VLOOKUP(BA1706,Selects!$B$4:$C$100,2,0),"") | BG1706: =IF(LEN(BF1706)=11,"PF",IF(LEN(BF1706)=14,"PJ","")) | BI1706: =IF(BH1706<>"",VLOOKUP(BH1706,Selects!$G:$H,2,0),"") | CB1706: =IF(AC1706<>"",VLOOKUP(AC1706,Selects!$B:$E,4,0),"")
E1707: =IF(LEN(D1707)=11,"PF",IF(LEN(D1707)=14,"PJ","")) | J1707: =IF(I1707<>"",VLOOKUP(I1707,'Legal Nature'!$E$2:$G$84,3,0),"") | AD1707: =IF(AC1707<>"",VLOOKUP(AC1707,Selects!$B$4:$C$100,2,0),"") | AM1707: =IF(LEFT(AL1707,1)="9","Celular",IF(AL1707="","","Fixo")) | AN1707: =IF( AM1707<>"",VLOOKUP(AM1707,Selects!$M$4:$N$1000,2,0),"") | BB1707: =IF(BA1707<>"",VLOOKUP(BA1707,Selects!$B$4:$C$100,2,0),"") | BG1707: =IF(LEN(BF1707)=11,"PF",IF(LEN(BF1707)=14,"PJ","")) | BI1707: =IF(BH1707<>"",VLOOKUP(BH1707,Selects!$G:$H,2,0),"") | CB1707: =IF(AC1707<>"",VLOOKUP(AC1707,Selects!$B:$E,4,0),"")
E1708: =IF(LEN(D1708)=11,"PF",IF(LEN(D1708)=14,"PJ","")) | J1708: =IF(I1708<>"",VLOOKUP(I1708,'Legal Nature'!$E$2:$G$84,3,0),"") | AD1708: =IF(AC1708<>"",VLOOKUP(AC1708,Selects!$B$4:$C$100,2,0),"") | AM1708: =IF(LEFT(AL1708,1)="9","Celular",IF(AL1708="","","Fixo")) | AN1708: =IF( AM1708<>"",VLOOKUP(AM1708,Selects!$M$4:$N$1000,2,0),"") | BB1708: =IF(BA1708<>"",VLOOKUP(BA1708,Selects!$B$4:$C$100,2,0),"") | BG1708: =IF(LEN(BF1708)=11,"PF",IF(LEN(BF1708)=14,"PJ","")) | BI1708: =IF(BH1708<>"",VLOOKUP(BH1708,Selects!$G:$H,2,0),"") | CB1708: =IF(AC1708<>"",VLOOKUP(AC1708,Selects!$B:$E,4,0),"")
E1709: =IF(LEN(D1709)=11,"PF",IF(LEN(D1709)=14,"PJ","")) | J1709: =IF(I1709<>"",VLOOKUP(I1709,'Legal Nature'!$E$2:$G$84,3,0),"") | AD1709: =IF(AC1709<>"",VLOOKUP(AC1709,Selects!$B$4:$C$100,2,0),"") | AM1709: =IF(LEFT(AL1709,1)="9","Celular",IF(AL1709="","","Fixo")) | AN1709: =IF( AM1709<>"",VLOOKUP(AM1709,Selects!$M$4:$N$1000,2,0),"") | BB1709: =IF(BA1709<>"",VLOOKUP(BA1709,Selects!$B$4:$C$100,2,0),"") | BG1709: =IF(LEN(BF1709)=11,"PF",IF(LEN(BF1709)=14,"PJ","")) | BI1709: =IF(BH1709<>"",VLOOKUP(BH1709,Selects!$G:$H,2,0),"") | CB1709: =IF(AC1709<>"",VLOOKUP(AC1709,Selects!$B:$E,4,0),"")
E1710: =IF(LEN(D1710)=11,"PF",IF(LEN(D1710)=14,"PJ","")) | J1710: =IF(I1710<>"",VLOOKUP(I1710,'Legal Nature'!$E$2:$G$84,3,0),"") | AD1710: =IF(AC1710<>"",VLOOKUP(AC1710,Selects!$B$4:$C$100,2,0),"") | AM1710: =IF(LEFT(AL1710,1)="9","Celular",IF(AL1710="","","Fixo")) | AN1710: =IF( AM1710<>"",VLOOKUP(AM1710,Selects!$M$4:$N$1000,2,0),"") | BB1710: =IF(BA1710<>"",VLOOKUP(BA1710,Selects!$B$4:$C$100,2,0),"") | BG1710: =IF(LEN(BF1710)=11,"PF",IF(LEN(BF1710)=14,"PJ","")) | BI1710: =IF(BH1710<>"",VLOOKUP(BH1710,Selects!$G:$H,2,0),"") | CB1710: =IF(AC1710<>"",VLOOKUP(AC1710,Selects!$B:$E,4,0),"")
E1711: =IF(LEN(D1711)=11,"PF",IF(LEN(D1711)=14,"PJ","")) | J1711: =IF(I1711<>"",VLOOKUP(I1711,'Legal Nature'!$E$2:$G$84,3,0),"") | AD1711: =IF(AC1711<>"",VLOOKUP(AC1711,Selects!$B$4:$C$100,2,0),"") | AM1711: =IF(LEFT(AL1711,1)="9","Celular",IF(AL1711="","","Fixo")) | AN1711: =IF( AM1711<>"",VLOOKUP(AM1711,Selects!$M$4:$N$1000,2,0),"") | BB1711: =IF(BA1711<>"",VLOOKUP(BA1711,Selects!$B$4:$C$100,2,0),"") | BG1711: =IF(LEN(BF1711)=11,"PF",IF(LEN(BF1711)=14,"PJ","")) | BI1711: =IF(BH1711<>"",VLOOKUP(BH1711,Selects!$G:$H,2,0),"") | CB1711: =IF(AC1711<>"",VLOOKUP(AC1711,Selects!$B:$E,4,0),"")
E1712: =IF(LEN(D1712)=11,"PF",IF(LEN(D1712)=14,"PJ","")) | J1712: =IF(I1712<>"",VLOOKUP(I1712,'Legal Nature'!$E$2:$G$84,3,0),"") | AD1712: =IF(AC1712<>"",VLOOKUP(AC1712,Selects!$B$4:$C$100,2,0),"") | AM1712: =IF(LEFT(AL1712,1)="9","Celular",IF(AL1712="","","Fixo")) | AN1712: =IF( AM1712<>"",VLOOKUP(AM1712,Selects!$M$4:$N$1000,2,0),"") | BB1712: =IF(BA1712<>"",VLOOKUP(BA1712,Selects!$B$4:$C$100,2,0),"") | BG1712: =IF(LEN(BF1712)=11,"PF",IF(LEN(BF1712)=14,"PJ","")) | BI1712: =IF(BH1712<>"",VLOOKUP(BH1712,Selects!$G:$H,2,0),"") | CB1712: =IF(AC1712<>"",VLOOKUP(AC1712,Selects!$B:$E,4,0),"")
E1713: =IF(LEN(D1713)=11,"PF",IF(LEN(D1713)=14,"PJ","")) | J1713: =IF(I1713<>"",VLOOKUP(I1713,'Legal Nature'!$E$2:$G$84,3,0),"") | AD1713: =IF(AC1713<>"",VLOOKUP(AC1713,Selects!$B$4:$C$100,2,0),"") | AM1713: =IF(LEFT(AL1713,1)="9","Celular",IF(AL1713="","","Fixo")) | AN1713: =IF( AM1713<>"",VLOOKUP(AM1713,Selects!$M$4:$N$1000,2,0),"") | BB1713: =IF(BA1713<>"",VLOOKUP(BA1713,Selects!$B$4:$C$100,2,0),"") | BG1713: =IF(LEN(BF1713)=11,"PF",IF(LEN(BF1713)=14,"PJ","")) | BI1713: =IF(BH1713<>"",VLOOKUP(BH1713,Selects!$G:$H,2,0),"") | CB1713: =IF(AC1713<>"",VLOOKUP(AC1713,Selects!$B:$E,4,0),"")
E1714: =IF(LEN(D1714)=11,"PF",IF(LEN(D1714)=14,"PJ","")) | J1714: =IF(I1714<>"",VLOOKUP(I1714,'Legal Nature'!$E$2:$G$84,3,0),"") | AD1714: =IF(AC1714<>"",VLOOKUP(AC1714,Selects!$B$4:$C$100,2,0),"") | AM1714: =IF(LEFT(AL1714,1)="9","Celular",IF(AL1714="","","Fixo")) | AN1714: =IF( AM1714<>"",VLOOKUP(AM1714,Selects!$M$4:$N$1000,2,0),"") | BB1714: =IF(BA1714<>"",VLOOKUP(BA1714,Selects!$B$4:$C$100,2,0),"") | BG1714: =IF(LEN(BF1714)=11,"PF",IF(LEN(BF1714)=14,"PJ","")) | BI1714: =IF(BH1714<>"",VLOOKUP(BH1714,Selects!$G:$H,2,0),"") | CB1714: =IF(AC1714<>"",VLOOKUP(AC1714,Selects!$B:$E,4,0),"")
E1715: =IF(LEN(D1715)=11,"PF",IF(LEN(D1715)=14,"PJ","")) | J1715: =IF(I1715<>"",VLOOKUP(I1715,'Legal Nature'!$E$2:$G$84,3,0),"") | AD1715: =IF(AC1715<>"",VLOOKUP(AC1715,Selects!$B$4:$C$100,2,0),"") | AM1715: =IF(LEFT(AL1715,1)="9","Celular",IF(AL1715="","","Fixo")) | AN1715: =IF( AM1715<>"",VLOOKUP(AM1715,Selects!$M$4:$N$1000,2,0),"") | BB1715: =IF(BA1715<>"",VLOOKUP(BA1715,Selects!$B$4:$C$100,2,0),"") | BG1715: =IF(LEN(BF1715)=11,"PF",IF(LEN(BF1715)=14,"PJ","")) | BI1715: =IF(BH1715<>"",VLOOKUP(BH1715,Selects!$G:$H,2,0),"") | CB1715: =IF(AC1715<>"",VLOOKUP(AC1715,Selects!$B:$E,4,0),"")
E1716: =IF(LEN(D1716)=11,"PF",IF(LEN(D1716)=14,"PJ","")) | J1716: =IF(I1716<>"",VLOOKUP(I1716,'Legal Nature'!$E$2:$G$84,3,0),"") | AD1716: =IF(AC1716<>"",VLOOKUP(AC1716,Selects!$B$4:$C$100,2,0),"") | AM1716: =IF(LEFT(AL1716,1)="9","Celular",IF(AL1716="","","Fixo")) | AN1716: =IF( AM1716<>"",VLOOKUP(AM1716,Selects!$M$4:$N$1000,2,0),"") | BB1716: =IF(BA1716<>"",VLOOKUP(BA1716,Selects!$B$4:$C$100,2,0),"") | BG1716: =IF(LEN(BF1716)=11,"PF",IF(LEN(BF1716)=14,"PJ","")) | BI1716: =IF(BH1716<>"",VLOOKUP(BH1716,Selects!$G:$H,2,0),"") | CB1716: =IF(AC1716<>"",VLOOKUP(AC1716,Selects!$B:$E,4,0),"")
E1717: =IF(LEN(D1717)=11,"PF",IF(LEN(D1717)=14,"PJ","")) | J1717: =IF(I1717<>"",VLOOKUP(I1717,'Legal Nature'!$E$2:$G$84,3,0),"") | AD1717: =IF(AC1717<>"",VLOOKUP(AC1717,Selects!$B$4:$C$100,2,0),"") | AM1717: =IF(LEFT(AL1717,1)="9","Celular",IF(AL1717="","","Fixo")) | AN1717: =IF( AM1717<>"",VLOOKUP(AM1717,Selects!$M$4:$N$1000,2,0),"") | BB1717: =IF(BA1717<>"",VLOOKUP(BA1717,Selects!$B$4:$C$100,2,0),"") | BG1717: =IF(LEN(BF1717)=11,"PF",IF(LEN(BF1717)=14,"PJ","")) | BI1717: =IF(BH1717<>"",VLOOKUP(BH1717,Selects!$G:$H,2,0),"") | CB1717: =IF(AC1717<>"",VLOOKUP(AC1717,Selects!$B:$E,4,0),"")
E1718: =IF(LEN(D1718)=11,"PF",IF(LEN(D1718)=14,"PJ","")) | J1718: =IF(I1718<>"",VLOOKUP(I1718,'Legal Nature'!$E$2:$G$84,3,0),"") | AD1718: =IF(AC1718<>"",VLOOKUP(AC1718,Selects!$B$4:$C$100,2,0),"") | AM1718: =IF(LEFT(AL1718,1)="9","Celular",IF(AL1718="","","Fixo")) | AN1718: =IF( AM1718<>"",VLOOKUP(AM1718,Selects!$M$4:$N$1000,2,0),"") | BB1718: =IF(BA1718<>"",VLOOKUP(BA1718,Selects!$B$4:$C$100,2,0),"") | BG1718: =IF(LEN(BF1718)=11,"PF",IF(LEN(BF1718)=14,"PJ","")) | BI1718: =IF(BH1718<>"",VLOOKUP(BH1718,Selects!$G:$H,2,0),"") | CB1718: =IF(AC1718<>"",VLOOKUP(AC1718,Selects!$B:$E,4,0),"")
... E1841: =IF(LEN(D1841)=11,"PF",IF(LEN(D1841)=14,"PJ","")) | J1841: =IF(I1841<>"",VLOOKUP(I1841,'Legal Nature'!$E$2:$G$84,3,0),"") | AD1841: =IF(AC1841<>"",VLOOKUP(AC1841,Selects!$B$4:$C$100,2,0),"") | AM1841: =IF(LEFT(AL1841,1)="9","Celular",IF(AL1841="","","Fixo")) | AN1841: =IF( AM1841<>"",VLOOKUP(AM1841,Selects!$M$4:$N$1000,2,0),"") | BB1841: =IF(BA1841<>"",VLOOKUP(BA1841,Selects!$B$4:$C$100,2,0),"") | BG1841: =IF(LEN(BF1841)=11,"PF",IF(LEN(BF1841)=14,"PJ","")) | BI1841: =IF(BH1841<>"",VLOOKUP(BH1841,Selects!$G:$H,2,0),"") | CB1841: =IF(AC1841<>"",VLOOKUP(AC1841,Selects!$B:$E,4,0),"")
E1842: =IF(LEN(D1842)=11,"PF",IF(LEN(D1842)=14,"PJ","")) | J1842: =IF(I1842<>"",VLOOKUP(I1842,'Legal Nature'!$E$2:$G$84,3,0),"") | AD1842: =IF(AC1842<>"",VLOOKUP(AC1842,Selects!$B$4:$C$100,2,0),"") | AM1842: =IF(LEFT(AL1842,1)="9","Celular",IF(AL1842="","","Fixo")) | AN1842: =IF( AM1842<>"",VLOOKUP(AM1842,Selects!$M$4:$N$1000,2,0),"") | BB1842: =IF(BA1842<>"",VLOOKUP(BA1842,Selects!$B$4:$C$100,2,0),"") | BG1842: =IF(LEN(BF1842)=11,"PF",IF(LEN(BF1842)=14,"PJ","")) | CB1842: =IF(AC1842<>"",VLOOKUP(AC1842,Selects!$B:$E,4,0),"")
E1843: =IF(LEN(D1843)=11,"PF",IF(LEN(D1843)=14,"PJ","")) | J1843: =IF(I1843<>"",VLOOKUP(I1843,'Legal Nature'!$E$2:$G$84,3,0),"") | AD1843: =IF(AC1843<>"",VLOOKUP(AC1843,Selects!$B$4:$C$100,2,0),"") | AM1843: =IF(LEFT(AL1843,1)="9","Celular",IF(AL1843="","","Fixo")) | AN1843: =IF( AM1843<>"",VLOOKUP(AM1843,Selects!$M$4:$N$1000,2,0),"") | BB1843: =IF(BA1843<>"",VLOOKUP(BA1843,Selects!$B$4:$C$100,2,0),"") | BG1843: =IF(LEN(BF1843)=11,"PF",IF(LEN(BF1843)=14,"PJ","")) | CB1843: =IF(AC1843<>"",VLOOKUP(AC1843,Selects!$B:$E,4,0),"")
E1844: =IF(LEN(D1844)=11,"PF",IF(LEN(D1844)=14,"PJ","")) | J1844: =IF(I1844<>"",VLOOKUP(I1844,'Legal Nature'!$E$2:$G$84,3,0),"") | AD1844: =IF(AC1844<>"",VLOOKUP(AC1844,Selects!$B$4:$C$100,2,0),"") | AM1844: =IF(LEFT(AL1844,1)="9","Celular",IF(AL1844="","","Fixo")) | AN1844: =IF( AM1844<>"",VLOOKUP(AM1844,Selects!$M$4:$N$1000,2,0),"") | BB1844: =IF(BA1844<>"",VLOOKUP(BA1844,Selects!$B$4:$C$100,2,0),"") | BG1844: =IF(LEN(BF1844)=11,"PF",IF(LEN(BF1844)=14,"PJ","")) | CB1844: =IF(AC1844<>"",VLOOKUP(AC1844,Selects!$B:$E,4,0),"")
E1845: =IF(LEN(D1845)=11,"PF",IF(LEN(D1845)=14,"PJ","")) | J1845: =IF(I1845<>"",VLOOKUP(I1845,'Legal Nature'!$E$2:$G$84,3,0),"") | AD1845: =IF(AC1845<>"",VLOOKUP(AC1845,Selects!$B$4:$C$100,2,0),"") | AM1845: =IF(LEFT(AL1845,1)="9","Celular",IF(AL1845="","","Fixo")) | AN1845: =IF( AM1845<>"",VLOOKUP(AM1845,Selects!$M$4:$N$1000,2,0),"") | BB1845: =IF(BA1845<>"",VLOOKUP(BA1845,Selects!$B$4:$C$100,2,0),"") | BG1845: =IF(LEN(BF1845)=11,"PF",IF(LEN(BF1845)=14,"PJ","")) | CB1845: =IF(AC1845<>"",VLOOKUP(AC1845,Selects!$B:$E,4,0),"")
E1846: =IF(LEN(D1846)=11,"PF",IF(LEN(D1846)=14,"PJ","")) | J1846: =IF(I1846<>"",VLOOKUP(I1846,'Legal Nature'!$E$2:$G$84,3,0),"") | AD1846: =IF(AC1846<>"",VLOOKUP(AC1846,Selects!$B$4:$C$100,2,0),"") | AM1846: =IF(LEFT(AL1846,1)="9","Celular",IF(AL1846="","","Fixo")) | AN1846: =IF( AM1846<>"",VLOOKUP(AM1846,Selects!$M$4:$N$1000,2,0),"") | BB1846: =IF(BA1846<>"",VLOOKUP(BA1846,Selects!$B$4:$C$100,2,0),"") | BG1846: =IF(LEN(BF1846)=11,"PF",IF(LEN(BF1846)=14,"PJ","")) | CB1846: =IF(AC1846<>"",VLOOKUP(AC1846,Selects!$B:$E,4,0),"")
E1847: =IF(LEN(D1847)=11,"PF",IF(LEN(D1847)=14,"PJ","")) | J1847: =IF(I1847<>"",VLOOKUP(I1847,'Legal Nature'!$E$2:$G$84,3,0),"") | AD1847: =IF(AC1847<>"",VLOOKUP(AC1847,Selects!$B$4:$C$100,2,0),"") | AM1847: =IF(LEFT(AL1847,1)="9","Celular",IF(AL1847="","","Fixo")) | AN1847: =IF( AM1847<>"",VLOOKUP(AM1847,Selects!$M$4:$N$1000,2,0),"") | BB1847: =IF(BA1847<>"",VLOOKUP(BA1847,Selects!$B$4:$C$100,2,0),"") | BG1847: =IF(LEN(BF1847)=11,"PF",IF(LEN(BF1847)=14,"PJ","")) | CB1847: =IF(AC1847<>"",VLOOKUP(AC1847,Selects!$B:$E,4,0),"")
E1848: =IF(LEN(D1848)=11,"PF",IF(LEN(D1848)=14,"PJ","")) | J1848: =IF(I1848<>"",VLOOKUP(I1848,'Legal Nature'!$E$2:$G$84,3,0),"") | AD1848: =IF(AC1848<>"",VLOOKUP(AC1848,Selects!$B$4:$C$100,2,0),"") | AM1848: =IF(LEFT(AL1848,1)="9","Celular",IF(AL1848="","","Fixo")) | AN1848: =IF( AM1848<>"",VLOOKUP(AM1848,Selects!$M$4:$N$1000,2,0),"") | BB1848: =IF(BA1848<>"",VLOOKUP(BA1848,Selects!$B$4:$C$100,2,0),"") | BG1848: =IF(LEN(BF1848)=11,"PF",IF(LEN(BF1848)=14,"PJ","")) | CB1848: =IF(AC1848<>"",VLOOKUP(AC1848,Selects!$B:$E,4,0),"")
E1849: =IF(LEN(D1849)=11,"PF",IF(LEN(D1849)=14,"PJ","")) | J1849: =IF(I1849<>"",VLOOKUP(I1849,'Legal Nature'!$E$2:$G$84,3,0),"") | AD1849: =IF(AC1849<>"",VLOOKUP(AC1849,Selects!$B$4:$C$100,2,0),"") | AM1849: =IF(LEFT(AL1849,1)="9","Celular",IF(AL1849="","","Fixo")) | AN1849: =IF( AM1849<>"",VLOOKUP(AM1849,Selects!$M$4:$N$1000,2,0),"") | BB1849: =IF(BA1849<>"",VLOOKUP(BA1849,Selects!$B$4:$C$100,2,0),"") | BG1849: =IF(LEN(BF1849)=11,"PF",IF(LEN(BF1849)=14,"PJ","")) | CB1849: =IF(AC1849<>"",VLOOKUP(AC1849,Selects!$B:$E,4,0),"")
...

Sheet Selects
B2: UF | E2: TIMEZONE | G2: BANCO | J2: CONTA BANCÁRIA | M2: TELEFONE | P2: MÉTODO DE PROCESSAMENTO | R2: DIAS DE FUNCIONAMENTO | U2: HORÁRIOS DE FUNCIONAMENTO | X2: TIPO DE CHAVE PIX | Z2: PIX
B4: AC | C4: BR | E4: UTC-05:00 | G4: ACCREDITO SCD S.A. | H4: 406 | J4: Corrente | K4: checking | M4: Fixo | N4: landline | P4: CNP - Cartão Não Presente | R4: Todos os Dias | S4: Every Day | U4: Horário Comercial | V4: business hours | X4: CPF | Z4: Sim
B5: AL | C5: BR | E5: UTC-03:00 | G5: ACESSO SOLUCOES PAGAMENTO SA | H5: 332 | J5: Poupança | K5: savings | M5: Celular | N5: mobile | P5: CP - Cartão Presente | R5: Segunda à Sexta | S5: Monday to Friday | U5: Manhã | V5: Morning | X5: CNPJ | Z5: Não
B6: AM | C6: BR | E6: UTC-03:00 | G6: ADVANCED CC LTDA | H6: 117 | J6: Depósito | K6: deposit | P6: Ambos | R6: Segunda à Sábado | S6: Monday to Saturday | U6: Tarde | V6: Evening | X6: Celular
B7: AP | C7: BR | E7: UTC-05:00 | G7: AGK CC S.A. | H7: 272 | J7: Pagamento | K7: payment | R7: Terça à Domingo | S7: Tuesdays to Sundays | U7: Noite | V7: Night | X7: E-mail
B8: BA | C8: BR | E8: UTC-03:00 | G8: AL5 S.A. CFI | H8: 349 | U8: 24 hrs | V8: 24-hour | X8: Chave aleatória
B9: CE | C9: BR | E9: UTC-03:00 | G9: ALBATROSS CCV S.A | H9: 172
B10: DF | C10: BR | E10: UTC-03:00 | G10: AMAZÔNIA CC LTDA. | H10: 313
B11: ES | C11: BR | E11: UTC-03:00 | G11: ASAAS IP S.A. | H11: 461
B12: GO | C12: BR | E12: UTC-03:00 | G12: ATIVA S.A. INVESTIMENTOS CCTVM | H12: 188
B13: MA | C13: BR | E13: UTC-03:00 | G13: AZUMI DTVM | H13: 463
B14: MG | C14: BR | E14: UTC-04:00 | G14: B&T CC LTDA. | H14: 080
B15: MS | C15: BR | E15: UTC-04:00 | G15: BANCO ALVORADA S.A. | H15: 641
B16: MT | C16: BR | E16: UTC-03:00 | G16: BANCO BARI S.A. | H16: 330
B17: PA | C17: BR | E17: UTC-03:00 | G17: BANCO BRADESCARD | H17: 063
B18: PB | C18: BR | E18: UTC-03:00 | G18: BANCO BRADESCO CARTÕES S.A. | H18: 204
B19: PE | C19: BR | E19: UTC-03:00 | G19: BANCO BTG PACTUAL S.A. | H19: 208
B20: PI | C20: BR | E20: UTC-03:00 | G20: BANCO CIFRA | H20: 233
... B30: TO | C30: BR | E30: UTC-03:00 | G30: BANCO MASTER | H30: 243
E31: - | G31: BANCO OLÉ CONSIGNADO S.A. | H31: 169
G32: BANCO ORIGINAL | H32: 212
G33: BANCO PAN | H33: 623
G34: BANCO RANDON S.A. | H34: 088
G35: BANCO SEMEAR | H35: 743
G36: BANCO SICOOB S.A. | H36: 756
G37: BANCO SISTEMA | H37: 754
G38: BANCO TOPÁZIO S.A. | H38: 082
G39: BANCO VOITER | H39: 653
G40: BANCOSEGURO S.A. | H40: 081
G41: BARI CIA HIPOTECÁRIA | H41: 268
G42: BBC LEASING | H42: 378
G43: BCO ABC BRASIL S.A. | H43: 246
... G324: ZOOP TECNOLOGIA & INSTITUIÇÃO DE PAGAMENTO S.A. | H324: 032

Sheet Cnae  mcc  id
A2: Cnae | C2: Denominação | E2: Seção CNAE | G2: Grupo CNAE | I2: MCC | K2: MCC Description | M2: ID
A3: 6201-5/01 | C3: Desenvolvimento de programas de computador sob encomenda | E3: INFORMAÇÃO E COMUNICAÇÃO | G3: ATIVIDADES DOS SERVIÇOS DE TECNOLOGIA DA INFORMAÇÃO | I3: 7372 | K3: Computer Programming, Data Processing, and Integrated Systems Design | M3: 1
A4: 6202-3/00 | C4: Desenvolvimento e licenciamento de programas de computador customizáveis | E4: INFORMAÇÃO E COMUNICAÇÃO | G4: ATIVIDADES DOS SERVIÇOS DE TECNOLOGIA DA INFORMAÇÃO | I4: 7372 | K4: Computer Programming, Data Processing, and Integrated Systems Design | M4: 1
A5: 6203-1/00 | C5: Desenvolvimento e licenciamento de programas de computador não-customizáveis | E5: INFORMAÇÃO E COMUNICAÇÃO | G5: ATIVIDADES DOS SERVIÇOS DE TECNOLOGIA DA INFORMAÇÃO | I5: 7372 | K5: Computer Programming, Data Processing, and Integrated Systems Design | M5: 1
A6: 6204-0/00 | C6: Consultoria em tecnologia da informação | E6: INFORMAÇÃO E COMUNICAÇÃO | G6: ATIVIDADES DOS SERVIÇOS DE TECNOLOGIA DA INFORMAÇÃO | I6: 7372 | K6: Computer Programming, Data Processing, and Integrated Systems Design | M6: 1
A7: 6201-5/00 | C7: Desenvolvimento de programas de computador sob encomenda | E7: NÃO ENCONTRADO | G7: NÃO ENCONTRADO | I7: 7372 | K7: Computer Programming, Data Processing, and Integrated Systems Design | M7: 1
A8: 4711-3/01 | C8: Comércio varejista de mercadorias em geral, com predominância de produtos alimentícios - hipermercados | E8: COMÉRCIO; REPARAÇÃO DE VEÍCULOS AUTOMOTORES E MOTOCICLETAS | G8: COMÉRCIO VAREJISTA | I8: 5411 | K8: Grocery Stores and Supermarkets | M8: 2
A9: 4711-3/02 | C9: Comércio varejista de mercadorias em geral, com predominância de produtos alimentícios - supermercados | E9: COMÉRCIO; REPARAÇÃO DE VEÍCULOS AUTOMOTORES E MOTOCICLETAS | G9: COMÉRCIO VAREJISTA | I9: 5411 | K9: Grocery Stores and Supermarkets | M9: 2
A10: 4712-1/00 | C10: Comércio varejista de mercadorias em geral, com predominância de produtos alimentícios - minimercados, mercearias e armazéns | E10: COMÉRCIO; REPARAÇÃO DE VEÍCULOS AUTOMOTORES E MOTOCICLETAS | G10: COMÉRCIO VAREJISTA | I10: 5411 | K10: Grocery Stores and Supermarkets | M10: 2
A11: 4619-2/00 | C11: Representantes comerciais e agentes do comércio de mercadorias em geral não especializado | E11: COMÉRCIO; REPARAÇÃO DE VEÍCULOS AUTOMOTORES E MOTOCICLETAS | G11: COMÉRCIO POR ATACADO, EXCETO VEÍCULOS AUTOMOTORES E MOTOCICLETAS | I11: 5300 | K11: Wholesale Clubs | M11: 3
A12: 4637-1/99 | C12: Comércio atacadista especializado em outros produtos alimentícios não especificados anteriormente | E12: COMÉRCIO; REPARAÇÃO DE VEÍCULOS AUTOMOTORES E MOTOCICLETAS | G12: COMÉRCIO POR ATACADO, EXCETO VEÍCULOS AUTOMOTORES E MOTOCICLETAS | I12: 5300 | K12: Wholesale Clubs | M12: 3
A13: 4639-7/01 | C13: Comércio atacadista de produtos alimentícios em geral | E13: COMÉRCIO; REPARAÇÃO DE VEÍCULOS AUTOMOTORES E MOTOCICLETAS | G13: COMÉRCIO POR ATACADO, EXCETO VEÍCULOS AUTOMOTORES E MOTOCICLETAS | I13: 5300 | K13: Wholesale Clubs | M13: 3
A14: 4639-7/02 | C14: Comércio atacadista de produtos alimentícios em geral, com atividade de fracionamento e acondicionamento associada | E14: COMÉRCIO; REPARAÇÃO DE VEÍCULOS AUTOMOTORES E MOTOCICLETAS | G14: COMÉRCIO POR ATACADO, EXCETO VEÍCULOS AUTOMOTORES E MOTOCICLETAS | I14: 5300 | K14: Wholesale Clubs | M14: 3
... A621: 4679-6/01 | C621: Comércio atacadista de tintas, vernizes e similares | E621: COMÉRCIO; REPARAÇÃO DE VEÍCULOS AUTOMOTORES E MOTOCICLETAS | G621: COMÉRCIO POR ATACADO, EXCETO VEÍCULOS AUTOMOTORES E MOTOCICLETAS | I621: 5198 | K621: Paints, Varnishes and Supplies | M621: 65
C622: COMÉRCIO VAREJISTA | I622: 5200 | M622: 66
A623: 4741-5/00 | C623: Comércio varejista de tintas e materiais para pintura | E623: COMÉRCIO; REPARAÇÃO DE VEÍCULOS AUTOMOTORES E MOTOCICLETAS | G623: COMÉRCIO VAREJISTA | I623: 5231 | K623: Glass, Paint, and Wallpaper Stores | M623: 67
A624: 4743-1/00 | C624: Comércio varejista de vidros | E624: COMÉRCIO; REPARAÇÃO DE VEÍCULOS AUTOMOTORES E MOTOCICLETAS | G624: COMÉRCIO VAREJISTA | I624: 5231 | K624: Glass, Paint, and Wallpaper Stores | M624: 67
A625: 4713-0/03 | C625: Lojas duty free de aeroportos internacionais | E625: COMÉRCIO; REPARAÇÃO DE VEÍCULOS AUTOMOTORES E MOTOCICLETAS | G625: COMÉRCIO VAREJISTA | I625: 5309 | K625: Duty Free Stores | M625: 68
A626: 4713-0/05 | C626: Lojas francas (Duty free) de aeroportos, portos e em fronteiras terrestres | E626: COMÉRCIO; REPARAÇÃO DE VEÍCULOS AUTOMOTORES E MOTOCICLETAS | G626: COMÉRCIO VAREJISTA | I626: 5309 | K626: Duty Free Stores | M626: 68
A627: 4713-0/01 | C627: Lojas de departamentos ou magazines | E627: COMÉRCIO; REPARAÇÃO DE VEÍCULOS AUTOMOTORES E MOTOCICLETAS | G627: COMÉRCIO VAREJISTA | I627: 5311 | K627: Department Stores | M627: 69
A628: 4713-0/04 | C628: Lojas de departamentos ou magazines, exceto lojas francas (Duty free) | E628: COMÉRCIO; REPARAÇÃO DE VEÍCULOS AUTOMOTORES E MOTOCICLETAS | G628: COMÉRCIO VAREJISTA | I628: 5311 | K628: Department Stores | M628: 69
A629: 2910-7/01 | C629: Fabricação de automóveis, camionetas e utilitários | E629: IND DE TRANSFORMAÇÃO | G629: FABRICAÇÃO DE VEÍCULOS AUTOMOTORES, REBOQUES E CARROCERIAS | I629: 5511 | K629: Car and Truck Dealers (New and Used) Sales, Service, Repairs, Parts, and Leasing | M629: 70
A630: 2920-4/01 | C630: Fabricação de caminhões e ônibus | E630: IND DE TRANSFORMAÇÃO | G630: FABRICAÇÃO DE VEÍCULOS AUTOMOTORES, REBOQUES E CARROCERIAS | I630: 5511 | K630: Car and Truck Dealers (New and Used) Sales, Service, Repairs, Parts, and Leasing | M630: 70
A631: 4511-1/01 | C631: Comércio a varejo de automóveis, camionetas e utilitários novos | E631: COMÉRCIO; REPARAÇÃO DE VEÍCULOS AUTOMOTORES E MOTOCICLETAS | G631: COMÉRCIO E REPARAÇÃO DE VEÍCULOS AUTOMOTORES E MOTOCICLETAS | I631: 5511 | K631: Car and Truck Dealers (New and Used) Sales, Service, Repairs, Parts, and Leasing | M631: 70
A632: 4511-1/03 | C632: Comércio por atacado de automóveis, camionetas e utilitários novos e usados | E632: COMÉRCIO; REPARAÇÃO DE VEÍCULOS AUTOMOTORES E MOTOCICLETAS | G632: COMÉRCIO E REPARAÇÃO DE VEÍCULOS AUTOMOTORES E MOTOCICLETAS | I632: 5511 | K632: Car and Truck Dealers (New and Used) Sales, Service, Repairs, Parts, and Leasing | M632: 70
A633: 4511-1/04 | C633: Comércio por atacado de caminhões novos e usados | E633: COMÉRCIO; REPARAÇÃO DE VEÍCULOS AUTOMOTORES E MOTOCICLETAS | G633: COMÉRCIO E REPARAÇÃO DE VEÍCULOS AUTOMOTORES E MOTOCICLETAS | I633: 5511 | K633: Car and Truck Dealers (New and Used) Sales, Service, Repairs, Parts, and Leasing | M633: 70
A634: 4511-1/05 | C634: Comércio por atacado de reboques e semi-reboques novos e usados | E634: COMÉRCIO; REPARAÇÃO DE VEÍCULOS AUTOMOTORES E MOTOCICLETAS | G634: COMÉRCIO E REPARAÇÃO DE VEÍCULOS AUTOMOTORES E MOTOCICLETAS | I634: 5511 | K634: Car and Truck Dealers (New and Used) Sales, Service, Repairs, Parts, and Leasing | M634: 70
... A647: 4541-2/06 | C647: Comércio a varejo de peças e acessórios novos para motocicletas e motonetas | E647: COMÉRCIO; REPARAÇÃO DE VEÍCULOS AUTOMOTORES E MOTOCICLETAS | G647: COMÉRCIO E REPARAÇÃO DE VEÍCULOS AUTOMOTORES E MOTOCICLETAS | I647: 5571 | K647: Motorcycle Shops and Dealers | M647: 73
A648: 4541-2/07 | C648: Comércio a varejo de peças e acessórios usados para motocicletas e motonetas | E648: COMÉRCIO; REPARAÇÃO DE VEÍCULOS AUTOMOTORES E MOTOCICLETAS | G648: COMÉRCIO E REPARAÇÃO DE VEÍCULOS AUTOMOTORES E MOTOCICLETAS | I648: 5571 | M648: 73
A649: 4542-1/01 | C649: Representantes comerciais e agentes do comércio de motocicletas e motonetas, peças e acessórios | E649: COMÉRCIO; REPARAÇÃO DE VEÍCULOS AUTOMOTORES E MOTOCICLETAS | G649: COMÉRCIO E REPARAÇÃO DE VEÍCULOS AUTOMOTORES E MOTOCICLETAS | I649: 5571 | K649: Motorcycle Shops and Dealers | M649: 73
A650: 4542-1/02 | C650: Comércio sob consignação de motocicletas e motonetas | E650: COMÉRCIO; REPARAÇÃO DE VEÍCULOS AUTOMOTORES E MOTOCICLETAS | G650: COMÉRCIO E REPARAÇÃO DE VEÍCULOS AUTOMOTORES E MOTOCICLETAS | I650: 5571 | K650: Motorcycle Shops and Dealers | M650: 73
A651: 3091-1/00 | C651: Fabricação de motocicletas, peças e acessórios | E651: NÃO ENCONTRADO | G651: NÃO ENCONTRADO | I651: 5571 | K651: Motorcycle Shops and Dealers | M651: 73
A652: 1422-3/00 | C652: Fabricação de artigos do vestuário, produzidos em malharias e tricotagens, exceto meias | E652: IND DE TRANSFORMAÇÃO | G652: CONFECÇÃO DE ARTIGOS DO VESTUÁRIO E ACESSÓRIOS | I652: 5651 | K652: Family Clothing Stores | M652: 74
A653: 4781-4/00 | C653: Comércio varejista de artigos do vestuário e acessórios | E653: COMÉRCIO; REPARAÇÃO DE VEÍCULOS AUTOMOTORES E MOTOCICLETAS | G653: COMÉRCIO VAREJISTA | I653: 5651 | K653: Family Clothing Stores | M653: 74
A654: 4762-8/00 | C654: Comércio varejista de discos, CDs, DVDs e fitas | E654: COMÉRCIO; REPARAÇÃO DE VEÍCULOS AUTOMOTORES E MOTOCICLETAS | G654: COMÉRCIO VAREJISTA | I654: 5735 | K654: Record Stores | M654: 75
A655: 5620-1/02 | C655: Serviços de alimentação para eventos e recepções - bufê | E655: ALOJAMENTO E ALIMENTAÇÃO | G655: ALIMENTAÇÃO | I655: 5811 | K655: Caterers | M655: 76
A656: 8230-0/02 | C656: Casas de festas e eventos | E656: ATIV ADM E SV COMPLEMENT | G656: SERVIÇOS DE ESCRITÓRIO, DE APOIO ADMINISTRATIVO E OUTROS SERVIÇOS PRESTADOS ÀS EMPRESAS | I656: 5811 | K656: Caterers | M656: 76
A657: 4785-7/01 | C657: Comércio varejista de antigüidades | E657: COMÉRCIO; REPARAÇÃO DE VEÍCULOS AUTOMOTORES E MOTOCICLETAS | G657: COMÉRCIO VAREJISTA | I657: 5932 | K657: Antique Shops – Sales, Repairs, and Restoration Services | M657: 77
A658: 9002-7/02 | C658: Restauração de obras de arte | E658: ARTES, CULTURA, ESPORTE E RECREAÇÃO | G658: ATIVIDADES ARTÍSTICAS, CRIATIVAS E DE ESPETÁCULOS | I658: 5932 | K658: Antique Shops – Sales, Repairs, and Restoration Services | M658: 77
A659: 4649-4/03 | C659: Comércio atacadista de bicicletas, triciclos e outros veículos recreativos | E659: COMÉRCIO; REPARAÇÃO DE VEÍCULOS AUTOMOTORES E MOTOCICLETAS | G659: COMÉRCIO POR ATACADO, EXCETO VEÍCULOS AUTOMOTORES E MOTOCICLETAS | I659: 5940 | K659: Bicycle Shops – Sales and Service | M659: 78
A660: 4763-6/03 | C660: Comércio varejista de bicicletas e triciclos; peças e acessórios | E660: COMÉRCIO; REPARAÇÃO DE VEÍCULOS AUTOMOTORES E MOTOCICLETAS | G660: COMÉRCIO VAREJISTA | I660: 5940 | K660: Bicycle Shops – Sales and Service | M660: 78
... A921: 4731-8/00 | C921: Comércio varejista de combustíveis para veículos automotores | E921: COMÉRCIO; REPARAÇÃO DE VEÍCULOS AUTOMOTORES E MOTOCICLETAS | G921: COMÉRCIO VAREJISTA | I921: 5541 | K921: Service Stations (With or without Ancillary Services) | M921: 129
A922: 4789-0/01 | C922: Comércio varejista de suvenires, bijuterias e artesanatos | E922: COMÉRCIO; REPARAÇÃO DE VEÍCULOS AUTOMOTORES E MOTOCICLETAS | G922: COMÉRCIO VAREJISTA | I922: 5631 | M922: 130
A923: 4782-2/01 | C923: Comércio varejista de calçados | E923: COMÉRCIO; REPARAÇÃO DE VEÍCULOS AUTOMOTORES E MOTOCICLETAS | G923: COMÉRCIO VAREJISTA | I923: 5661 | K923: Shoe Stores | M923: 131
A924: 4755-5/03 | C924: Comercio varejista de artigos de cama, mesa e banho | E924: COMÉRCIO; REPARAÇÃO DE VEÍCULOS AUTOMOTORES E MOTOCICLETAS | G924: COMÉRCIO VAREJISTA | I924: 5719 | K924: Miscellaneous House Furnishing Specialty Shops | M924: 132
A925: 4753-9/00 | C925: Comércio varejista especializado de eletrodomésticos e equipamentos de áudio e vídeo | E925: COMÉRCIO; REPARAÇÃO DE VEÍCULOS AUTOMOTORES E MOTOCICLETAS | G925: COMÉRCIO VAREJISTA | I925: 5722 | K925: Household Appliance Stores | M925: 133
A926: 4757-1/00 | C926: Comércio varejista especializado de peças e acessórios para aparelhos eletroeletrônicos para uso doméstico, exceto informática e comunicação | E926: COMÉRCIO; REPARAÇÃO DE VEÍCULOS AUTOMOTORES E MOTOCICLETAS | G926: COMÉRCIO VAREJISTA | I926: 5732 | K926: Electronics Stores | M926: 134
A927: 4756-3/00 | C927: Comércio varejista especializado de instrumentos musicais e acessórios | E927: COMÉRCIO; REPARAÇÃO DE VEÍCULOS AUTOMOTORES E MOTOCICLETAS | G927: COMÉRCIO VAREJISTA | I927: 5733 | K927: Music Stores – Musical Instruments, Pianos, and Sheet Music | M927: 135
A928: 4771-7/01 | C928: Comércio varejista de produtos farmacêuticos, sem manipulação de fórmulas | E928: COMÉRCIO; REPARAÇÃO DE VEÍCULOS AUTOMOTORES E MOTOCICLETAS | G928: COMÉRCIO VAREJISTA | I928: 5912 | K928: Drug Stores and Pharmacies | M928: 136
A929: 4771-7/02 | C929: Comércio varejista de produtos farmacêuticos, com manipulação de fórmulas | E929: COMÉRCIO; REPARAÇÃO DE VEÍCULOS AUTOMOTORES E MOTOCICLETAS | G929: COMÉRCIO VAREJISTA | I929: 5912 | K929: Drug Stores and Pharmacies | M929: 136
A930: 4771-7/03 | C930: Comércio varejista de produtos farmacêuticos homeopáticos | E930: COMÉRCIO; REPARAÇÃO DE VEÍCULOS AUTOMOTORES E MOTOCICLETAS | G930: COMÉRCIO VAREJISTA | I930: 5912 | K930: Drug Stores and Pharmacies | M930: 136
A931: 4771-7/04 | C931: Comércio varejista de medicamentos veterinários | E931: COMÉRCIO; REPARAÇÃO DE VEÍCULOS AUTOMOTORES E MOTOCICLETAS | G931: COMÉRCIO VAREJISTA | I931: 5912 | K931: Drug Stores and Pharmacies | M931: 136
A932: 4763-6/01 | C932: Comércio varejista de brinquedos e artigos recreativos | E932: COMÉRCIO; REPARAÇÃO DE VEÍCULOS AUTOMOTORES E MOTOCICLETAS | G932: COMÉRCIO VAREJISTA | I932: 5945 | K932: Hobby, Toy, and Game Shops | M932: 137
A933: 4782-2/02 | C933: Comércio varejista de artigos de viagem | E933: COMÉRCIO; REPARAÇÃO DE VEÍCULOS AUTOMOTORES E MOTOCICLETAS | G933: COMÉRCIO VAREJISTA | I933: 5947 | K933: Card, Gift, Novelty, and Souvenir Shops | M933: 138
A934: 4789-0/01 | C934: Comércio varejista de suvenires, bijuterias e artesanatos | E934: COMÉRCIO; REPARAÇÃO DE VEÍCULOS AUTOMOTORES E MOTOCICLETAS | G934: COMÉRCIO VAREJISTA | I934: 5947 | K934: Card, Gift, Novelty, and Souvenir Shops | M934: 138
... A1225: 8630-5/03 | C1225: Atividade médica ambulatorial restrita a consultas | E1225: SAÚDE HUMANA E SV SOCIAIS | G1225: ATIVIDADES DE ATENÇÃO À SAÚDE HUMANA | I1225: 8011 | K1225: Doctors—not elsewhere classified | M1225: 193
C1226: Venda Porta a Porta | I1226: 5963 | K1226: Door-To-Door Sales | M1226: 194
A1227: 7410-2/01 | C1227: Design | E1227: NÃO ENCONTRADO | G1227: NÃO ENCONTRADO | I1227: 7333 | K1227: Commercial Photography, Art, and Graphics I | M1227: 195
A1228: 4759-8/99 | C1228: Comércio varejista de outros artigos de uso pessoal e doméstico não especificados anteriormente | E1228: COMÉRCIO; REPARAÇÃO DE VEÍCULOS AUTOMOTORES E MOTOCICLETAS | G1228: COMÉRCIO VAREJISTA | I1228: 5999 | K1228: Miscellaneous and Specialty Retail Stores | M1228: 196
A1229: 4789-0/05 | C1229: Comércio varejista de produtos saneantes domissanitários | E1229: COMÉRCIO; REPARAÇÃO DE VEÍCULOS AUTOMOTORES E MOTOCICLETAS | G1229: COMÉRCIO VAREJISTA | I1229: 5999 | K1229: Miscellaneous and Specialty Retail Stores | M1229: 196
A1230: 4789-0/06 | C1230: Comércio varejista de fogos de artifício e artigos pirotécnicos | E1230: COMÉRCIO; REPARAÇÃO DE VEÍCULOS AUTOMOTORES E MOTOCICLETAS | G1230: COMÉRCIO VAREJISTA | I1230: 5999 | K1230: Miscellaneous and Specialty Retail Stores | M1230: 196
A1231: 4789-0/09 | C1231: Comércio varejista de armas e munições | E1231: COMÉRCIO; REPARAÇÃO DE VEÍCULOS AUTOMOTORES E MOTOCICLETAS | G1231: COMÉRCIO VAREJISTA | I1231: 5999 | K1231: Miscellaneous and Specialty Retail Stores | M1231: 196
A1232: 4789-0/99 | C1232: Comércio varejista de outros produtos não especificados anteriormente | E1232: COMÉRCIO; REPARAÇÃO DE VEÍCULOS AUTOMOTORES E MOTOCICLETAS | G1232: COMÉRCIO VAREJISTA | I1232: 5999 | K1232: Miscellaneous and Specialty Retail Stores | M1232: 196
A1233: 2330-3/05 | C1233: Preparação de massa de concreto e argamassa para construção | E1233: IND DE TRANSFORMAÇÃO | G1233: FABRICAÇÃO DE PRODUTOS DE MINERAIS NÃO-METÁLICOS | I1233: 1771 | K1233: Concrete Work Contractors
A1234: 4211-1/01 | C1234: Construção de rodovias e ferrovias | E1234: CONSTRUÇÃO | G1234: OBRAS DE INFRA-ESTRUTURA | I1234: 1771 | K1234: Concrete Work Contractors
A1235: 4213-8/00 | C1235: Obras de urbanização - ruas, praças e calçadas | E1235: CONSTRUÇÃO | G1235: OBRAS DE INFRA-ESTRUTURA | I1235: 1771 | K1235: Concrete Work Contractors
A1236: 4311-8/02 | C1236: Preparação de canteiro e limpeza de terreno | E1236: CONSTRUÇÃO | G1236: SERVIÇOS ESPECIALIZADOS PARA CONSTRUÇÃO | I1236: 1771 | K1236: Concrete Work Contractors
A1237: 4391-6/00 | C1237: Obras de fundações | E1237: CONSTRUÇÃO | G1237: SERVIÇOS ESPECIALIZADOS PARA CONSTRUÇÃO | I1237: 1771 | K1237: Concrete Work Contractors
A1238: 5012-2/02 | C1238: Transporte marítimo de longo curso - Passageiros | E1238: TRANSPORTE, ARMAZENAGEM E CORREIO | G1238: TRANSPORTE AQUAVIÁRIO | I1238: 4411 | K1238: Steamship and Cruise Lines
A1239: 5232-0/00 | C1239: Atividades de agenciamento marítimo | E1239: TRANSPORTE, ARMAZENAGEM E CORREIO | G1239: ARMAZENAMENTO E ATIVIDADES AUXILIARES DOS TRANSPORTES | I1239: 4411 | K1239: Steamship and Cruise Lines
A1240: 5111-1/00 | C1240: Transporte aéreo de passageiros regular | E1240: TRANSPORTE, ARMAZENAGEM E CORREIO | G1240: TRANSPORTE AÉREO | I1240: 4511 | K1240: Airlines and Air Carriers (Not Elsewhere Classified)
A1241: 5112-9/01 | C1241: Serviço de táxi aéreo e locação de aeronaves com tripulação | E1241: TRANSPORTE, ARMAZENAGEM E CORREIO | G1241: TRANSPORTE AÉREO | I1241: 4511 | K1241: Airlines and Air Carriers (Not Elsewhere Classified)
A1242: 5112-9/99 | C1242: Outros serviços de transporte aéreo de passageiros não-regular | E1242: TRANSPORTE, ARMAZENAGEM E CORREIO | G1242: TRANSPORTE AÉREO | I1242: 4511 | K1242: Airlines and Air Carriers (Not Elsewhere Classified)
A1243: 5120-0/00 | C1243: Transporte aéreo de carga | E1243: TRANSPORTE, ARMAZENAGEM E CORREIO | G1243: TRANSPORTE AÉREO | I1243: 4511 | K1243: Airlines and Air Carriers (Not Elsewhere Classified)
A1244: 7911-2/00 | C1244: Agências de viagens | E1244: ATIV ADM E SV COMPLEMENT | G1244: AGÊNCIAS DE VIAGENS, OPERADORES TURÍSTICOS E SERVIÇOS DE RESERVAS | I1244: 4722 | K1244: Travel Agencies and Tour Operators H
... A1361: 9491-0/00 | C1361: Atividades de organizações religiosas ou filosóficas | E1361: OUTRAS ATIV DE SV | G1361: ATIVIDADES DE ORGANIZAÇÕES ASSOCIATIVAS | I1361: 8661 | K1361: Religious Organizations

Sheet Legal Nature
A1: Code | C1: Descrição | E1: Descrição | G1: Code
A2: 101-5 | C2: Órgão Público do Poder Executivo Federal | E2: Órgão Público do Poder Executivo Federal | G2: 101-5
A3: 102-3 | C3: Órgão Público do Poder Executivo Estadual ou do Distrito Federal | E3: Órgão Público do Poder Executivo Estadual ou do Distrito Federal | G3: 102-3
A4: 103-1 | C4: Órgão Público do Poder Executivo Municipal | E4: Órgão Público do Poder Executivo Municipal | G4: 103-1
A5: 104-0 | C5: Órgão Público do Poder Legislativo Federal | E5: Órgão Público do Poder Legislativo Federal | G5: 104-0
A6: 105-8 | C6: Órgão Público do Poder Legislativo Estadual ou do Distrito Federal | E6: Órgão Público do Poder Legislativo Estadual ou do Distrito Federal | G6: 105-8
A7: 106-6 | C7: Órgão Público do Poder Legislativo Municipal | E7: Órgão Público do Poder Legislativo Municipal | G7: 106-6
A8: 107-4 | C8: Órgão Público do Poder Judiciário Federal | E8: Órgão Público do Poder Judiciário Federal | G8: 107-4
A9: 108-2 | C9: Órgão Público do Poder Judiciário Estadual | E9: Órgão Público do Poder Judiciário Estadual | G9: 108-2
A10: 110-4 | C10: Autarquia Federal | E10: Autarquia Federal | G10: 110-4
A11: 111-2 | C11: Autarquia Estadual ou do Distrito Federal | E11: Autarquia Estadual ou do Distrito Federal | G11: 111-2
A12: 112-0 | C12: Autarquia Municipal | E12: Autarquia Municipal | G12: 112-0
... A84: 503-7 | C84: Outras Instituições Extraterritoriais | E84: Outras Instituições Extraterritoriais | G84: 503-7
